{"name":"TestGetEntry","fullName":"TestEntryTestIntegrationSuite/EntryTestIntegrationSuite/TestGetEntry","status":"failed","statusDetails":{"message":"\tError:      \tNot equal: \n\t            \texpected: map[string]interface {}{\"body\":map[string]interface {}{\"description\":\"entry\", \"duration\":\"2h0m0s\", \"id\":1, \"project_id\":interface {}(nil), \"tag_list\":[]interface {}{}, \"time_end\":\"2021-08-15T16:30:45+03:00\", \"time_start\":\"2021-08-15T14:30:45+03:00\", \"user_id\":1}}\n\t            \tactual  : map[string]interface {}{\"body\":map[string]interface {}{\"description\":\"entry\", \"duration\":\"2h0m0s\", \"id\":1, \"project_id\":interface {}(nil), \"tag_list\":[]interface {}{map[string]interface {}{\"About\":\"FBqdwkwpYncTYQgwhMnyUqtei\", \"Color\":\"SSindaNAHWEkBukErBsoXNSAX\", \"ID\":60, \"Name\":\"kykZXjMpnPxCRdHHUlOIKlOEC\", \"UserID\":8}, map[string]interface {}{\"About\":\"DQlDzkeQJScLPIwpwDrcRMknE\", \"Color\":\"AhxrXMmRSdbIeAywJQMXeKxxT\", \"ID\":1, \"Name\":\"iywbvukPXRwmdzNfLGEbjCcFE\", \"UserID\":94}, map[string]interface {}{\"About\":\"DilxvBJzNwrQcrsVAuJdkFaNz\", \"Color\":\"IyVKWsQDqUfyADWddPnuhRbyJ\", \"ID\":46, \"Name\":\"gQoNzbRRLafHhDEwKtcqMlvif\", \"UserID\":57}, map[string]interface {}{\"About\":\"BzXKpNiYEMfQsmpMBtwlDagmQ\", \"Color\":\"gFgayYvtzMkGJDeEgOeOUtfmf\", \"ID\":40, \"Name\":\"yTAkPWimHaNYCrHybsThPInyG\", \"UserID\":25}, map[string]interface {}{\"About\":\"qpjLVSxtFDtNYkFWasVJWdkWS\", \"Color\":\"OYXOqPuUcTpHBacrtyYrkVmJf\", \"ID\":97, \"Name\":\"cXdtYjaPFRhYpXcFDIxwmWbwM\", \"UserID\":44}, map[string]interface {}{\"About\":\"acqinUInZRwbgGSesFsXghAEc\", \"Color\":\"zSYkDEHujMgtSWrbqsUzIgREX\", \"ID\":20, \"Name\":\"FvNUdqLCPtzipNQQicbcrbRUU\", \"UserID\":99}, map[string]interface {}{\"About\":\"kWAhVlghoDEfZLEXEaiOBfoha\", \"Color\":\"CgZCNGWYZxHvWgyMASGehQgxK\", \"ID\":40, \"Name\":\"oUkDRstEOAnfwrHZRskRzcjsG\", \"UserID\":24}, map[string]interface {}{\"About\":\"MnRkAqCvJFtBieQBjraOulMFV\", \"Color\":\"EkQojCOfPWbFDgYrbkSTnAFYg\", \"ID\":12, \"Name\":\"vOqeiPsgidyMuygEwWpXkiRIO\", \"UserID\":79}, map[string]interface {}{\"About\":\"eTmFfQqRjdtcERHQCFuHihspp\", \"Color\":\"QLGMIwUSezmqTrgnkyetKoYgF\", \"ID\":7, \"Name\":\"WGRmYFLLDTUKXZzsLDNWxTOhz\", \"UserID\":20}, map[string]interface {}{\"About\":\"GNCUpxumMfaEVglXPoICthHxd\", \"Color\":\"KwUhADqtyXGLRMYZGpfMgyMbp\", \"ID\":67, \"Name\":\"DvkksZGiHwEzQTTSzikeCiJTE\", \"UserID\":43}, map[string]interface {}{\"About\":\"DmFmkhqPOQWolwJSLVmPlwmyd\", \"Color\":\"DpnBgkxFHmCmzujesUDtapiFf\", \"ID\":15, \"Name\":\"xgsxspZZFiHqDBzTvuEmugpfT\", \"UserID\":95}, map[string]interface {}{\"About\":\"WRPjsZQpFfmDTLfaEVAfvnZku\", \"Color\":\"AMolqtClqCZlGYnbCgrZAEKYm\", \"ID\":47, \"Name\":\"IORXqCjeJaIpNrxBgYuwNQEvs\", \"UserID\":61}, map[string]interface {}{\"About\":\"cXIKhgwWusZWCYLGqOOyFFWZi\", \"Color\":\"hOHFcCTUzCDkEuYhMTrzVMuOJ\", \"ID\":78, \"Name\":\"BCwaAcTDohuDIxMyOmhDucDLJ\", \"UserID\":24}, map[string]interface {}{\"About\":\"AJDvEGIVqHhWbfZLNlZCrakUV\", \"Color\":\"gnxBrFmGFdfeCLtjoXbFnRnom\", \"ID\":32, \"Name\":\"TUEsnkUvOvPmBzbrMVlHkJBgX\", \"UserID\":32}, map[string]interface {}{\"About\":\"SlDaXdDQsaSzFJJEOqZRtIDWW\", \"Color\":\"zotPbBCEWlZLzDphmCNwivMOD\", \"ID\":49, \"Name\":\"zyKjsJpSbJZvEjQodffkbTQUn\", \"UserID\":65}, map[string]interface {}{\"About\":\"AquvSfhZxaflPFCSNJcmgiOel\", \"Color\":\"OhUAdxwYbaWoVaHKePmMVsQgn\", \"ID\":94, \"Name\":\"YuZJAHgEQPYnblKXmFlLVJysV\", \"UserID\":40}, map[string]interface {}{\"About\":\"zvxVoKyDtuiGpxneVMacnFgxB\", \"Color\":\"NcygDnUtflioLfyXpntkpgZLO\", \"ID\":76, \"Name\":\"OXgJnatcVWGOKgbfYnJqQwtaC\", \"UserID\":67}, map[string]interface {}{\"About\":\"mYDEdCGKyBgGWNrgQcWiWmdOB\", \"Color\":\"GexziBOwmXfzIywMgAqMzGuiU\", \"ID\":1, \"Name\":\"EvZEOKGSNYcNuIIjykArugpuQ\", \"UserID\":7}, map[string]interface {}{\"About\":\"tEbxklfeiLroOVdlzTJwsielG\", \"Color\":\"ogdUsEwqJplBPxGFRSVdDiOHs\", \"ID\":77, \"Name\":\"dKFdfLMQMzGLsorUDHBYatadh\", \"UserID\":26}, map[string]interface {}{\"About\":\"lMMWdqjHgXtkHSyJhQdLDxOQA\", \"Color\":\"VmadUrsyLJATgaaiJJeoRaljZ\", \"ID\":37, \"Name\":\"IDDlbPXVMEaffnUkutJWpWSnM\", \"UserID\":1}, map[string]interface {}{\"About\":\"DrMzDVcvHCtSGpyBGjndfZKMk\", \"Color\":\"MJvLBgcnbtDgGlcIZZtcQTTtg\", \"ID\":16, \"Name\":\"PmVXaBnYHUOOheTcRfYahjzOw\", \"UserID\":45}, map[string]interface {}{\"About\":\"CTOCExlWuAHBZWxnIPrUpprPJ\", \"Color\":\"tPKlAuMZbronlMkLAwVLSAfrG\", \"ID\":50, \"Name\":\"VmSoqHzpmpZNxlnFtXFCgcHXa\", \"UserID\":45}, map[string]interface {}{\"About\":\"wMsytEGWQCPNvBxGaNSGLgFuW\", \"Color\":\"VSMOZXFDMdvPrfCFRQahZpeJi\", \"ID\":0, \"Name\":\"byrCrWITDlCOUQFwbKASqqYOk\", \"UserID\":49}, map[string]interface {}{\"About\":\"FVjtOcDFenwnPasNYArYiFJpU\", \"Color\":\"lhIXdvKsAKTNHFPsCMmxaJcAw\", \"ID\":25, \"Name\":\"puMZYvHrxpIgjALTadDknWeHb\", \"UserID\":41}, map[string]interface {}{\"About\":\"MmZafZzDdbGQSNzCqhsDwFXcQ\", \"Color\":\"zxoPtEzvPMdNMHmdDFvibSaUr\", \"ID\":90, \"Name\":\"DYrbyUgUerxmPnucvyodadTkJ\", \"UserID\":21}, map[string]interface {}{\"About\":\"hLzmfGogKYewiypMDSpCRGHkB\", \"Color\":\"mcRSfXgNjLXPvrAfBRAmdANIT\", \"ID\":50, \"Name\":\"FXvTbVTbKZxZYyMlULROLjXtP\", \"UserID\":24}, map[string]interface {}{\"About\":\"EOBkDlbBmbGioyUGhSSxTKonk\", \"Color\":\"dIborAbaRFLPzWQYpigfCLTtc\", \"ID\":49, \"Name\":\"HoOMKKsZEOuTcHNbpRjfQkkJo\", \"UserID\":86}, map[string]interface {}{\"About\":\"sJpEnQWROhvzZTGVJJrVdlxqz\", \"Color\":\"xMSlwufhrbeAQDmKlzWpwOfqY\", \"ID\":2, \"Name\":\"EhZgAqSVPkOWvtvDHkvwBoBxh\", \"UserID\":47}, map[string]interface {}{\"About\":\"NmNhSwYoMCSFjxwSDuySwYJRT\", \"Color\":\"HYIqFwIhYpMEsvyacmfXtVdSX\", \"ID\":83, \"Name\":\"bKtaMKaTohdQxOIQLgmUETLGR\", \"UserID\":77}, map[string]interface {}{\"About\":\"qDhMtHxFIaZdJdVyzIpYFucto\", \"Color\":\"JIkjyoJMBAKKEcYqBFbzMeGDR\", \"ID\":43, \"Name\":\"GcvmNdJsISAWPzkdZlgpCgPyk\", \"UserID\":1}, map[string]interface {}{\"About\":\"pqggXcQFpGkKIjOHWdxcbRXsK\", \"Color\":\"GWaEMvJiqbieQZZMydQPhTvAn\", \"ID\":92, \"Name\":\"rWOKoHdNkAYnkcXFerycGXZaF\", \"UserID\":3}, map[string]interface {}{\"About\":\"wbdPZNEMnOXKLgKQruVHyTNtp\", \"Color\":\"jkApwbrepJccNGaOGHpuwlwxZ\", \"ID\":76, \"Name\":\"rYxYUhOUuguQZqTGxLMovzUtH\", \"UserID\":24}, map[string]interface {}{\"About\":\"jeXqLWSuNDPdCsvLHnoLCkBFV\", \"Color\":\"UAOnqfkPdPKHlnScjkwYrjKYr\", \"ID\":19, \"Name\":\"COdgBIzxaQlZglRoCqJiVxTAk\", \"UserID\":92}, map[string]interface {}{\"About\":\"hANgjWfWkQjvsoURboarADLzk\", \"Color\":\"tBwqKNsZZLkQWBnQEEkcIAaqw\", \"ID\":2, \"Name\":\"TgjgyXcVLoIsDeGLppkrulGpV\", \"UserID\":43}, map[string]interface {}{\"About\":\"LoExNLuhTtBmvhzrzVkNucnjl\", \"Color\":\"ebuihoQwqZxFcltmvLESjovGx\", \"ID\":96, \"Name\":\"sUNUHYwhTYFhoSBKlpTvItxjS\", \"UserID\":48}, map[string]interface {}{\"About\":\"XZJqlcwNAJUShGxmmTgDYZaHy\", \"Color\":\"nxWXWgsnTFMIWqdleGjsKOGHD\", \"ID\":55, \"Name\":\"WouGVQxDMxnYKSLVApdbhaqTp\", \"UserID\":57}, map[string]interface {}{\"About\":\"rZVdfehCwPhekZRRVZCnTRtIn\", \"Color\":\"ysjddhhTdvDcRgGshOhuyWTDc\", \"ID\":16, \"Name\":\"miUIIuhwiXCsttHuJWWoXDuCz\", \"UserID\":76}, map[string]interface {}{\"About\":\"uGHkiFXWCqiBKNsyStqZJhsSh\", \"Color\":\"YCpCayxilRbnTdujYuKrMOGYl\", \"ID\":76, \"Name\":\"pELHXvATHBSOUCyvfmyNaSBbW\", \"UserID\":93}, map[string]interface {}{\"About\":\"wwYjjCyvwDSMnAQxmQBdTeYRd\", \"Color\":\"eCWtnvWmkUxGzHsfrRHRDoJyx\", \"ID\":94, \"Name\":\"ZUforRAvxSBwdZisqmGyQHGoG\", \"UserID\":30}, map[string]interface {}{\"About\":\"xyfDfcYBYssSORvmikhSLcuyG\", \"Color\":\"eoGoZAtKQnczfPPWPughOSEgI\", \"ID\":53, \"Name\":\"dmsWUCgBIjUSvnekgeoqrXKYR\", \"UserID\":80}, map[string]interface {}{\"About\":\"pQiOOONtbVaSQwMoyybWuoVBz\", \"Color\":\"rgGhWzoaJRmxhLisvqgTuDJXz\", \"ID\":4, \"Name\":\"NSuXYKfilgvHBDWzCBiFQVwWf\", \"UserID\":49}, map[string]interface {}{\"About\":\"gfgbOxyMNTFzuZLMcneczCMTu\", \"Color\":\"GdvXJhxUsHarvZdDyGjjcjErO\", \"ID\":10, \"Name\":\"MpPcxFPsApIbTGpMLzoUzHFvW\", \"UserID\":74}, map[string]interface {}{\"About\":\"ekoFctoxzNVzioSuGZZdbZUnw\", \"Color\":\"sUtfNMwwIofrigIiCSoxCfmbH\", \"ID\":76, \"Name\":\"hyliSrckXcoKArloyQdEWRsSs\", \"UserID\":15}, map[string]interface {}{\"About\":\"lJZMuuGEdElVCrXvchuwqGbPj\", \"Color\":\"JUxogvLyZphBaQzTrEcAMyBYO\", \"ID\":15, \"Name\":\"dXmulEWSOYVSeFrFQjBpKpIhz\", \"UserID\":88}, map[string]interface {}{\"About\":\"rkcSpIysBucfWbEQMLMhXiAmA\", \"Color\":\"uKAudzmrtlOwzNaMicBfGULoR\", \"ID\":10, \"Name\":\"wVWjzEbVxqPKMtYuPTLvZgNFy\", \"UserID\":34}, map[string]interface {}{\"About\":\"JcsKTqdUgGkdSqUjVdFioMYCO\", \"Color\":\"SINnkFDYIDFWolYjzSpfflrHe\", \"ID\":33, \"Name\":\"zzAgmHRnBOgaqCFvZSAqrdedD\", \"UserID\":81}, map[string]interface {}{\"About\":\"VOnBZXtRtAVADUktahQrGXrBM\", \"Color\":\"HuoEzfLlpJDtRPhTGLpMBKCzC\", \"ID\":2, \"Name\":\"BaXSywAdJczPtnNJZxilsBwxw\", \"UserID\":11}, map[string]interface {}{\"About\":\"dMOFhZBKiTJHsFkvjDsmxCGYK\", \"Color\":\"WOEiZGVbIWZWunzJBKGBQdwfV\", \"ID\":44, \"Name\":\"aBxOyAkeLPfzYNJDuhkTjUdPz\", \"UserID\":75}}, \"time_end\":\"2021-08-15T16:30:45+03:00\", \"time_start\":\"2021-08-15T14:30:45+03:00\", \"user_id\":1}}\n\t            \t\n\t            \tDiff:\n\t            \t--- Expected\n\t            \t+++ Actual\n\t            \t@@ -6,3 +6,339 @@\n\t            \t   (string) (len=10) \"project_id\": (interface {}) \u003cnil\u003e,\n\t            \t-  (string) (len=8) \"tag_list\": ([]interface {}) {\n\t            \t+  (string) (len=8) \"tag_list\": ([]interface {}) (len=48) {\n\t            \t+   (map[string]interface {}) (len=5) {\n\t            \t+    (string) (len=5) \"About\": (string) (len=25) \"FBqdwkwpYncTYQgwhMnyUqtei\",\n\t            \t+    (string) (len=5) \"Color\": (string) (len=25) \"SSindaNAHWEkBukErBsoXNSAX\",\n\t            \t+    (string) (len=2) \"ID\": (float64) 60,\n\t            \t+    (string) (len=4) \"Name\": (string) (len=25) \"kykZXjMpnPxCRdHHUlOIKlOEC\",\n\t            \t+    (string) (len=6) \"UserID\": (float64) 8\n\t            \t+   },\n\t            \t+   (map[string]interface {}) (len=5) {\n\t            \t+    (string) (len=5) \"About\": (string) (len=25) \"DQlDzkeQJScLPIwpwDrcRMknE\",\n\t            \t+    (string) (len=5) \"Color\": (string) (len=25) \"AhxrXMmRSdbIeAywJQMXeKxxT\",\n\t            \t+    (string) (len=2) \"ID\": (float64) 1,\n\t            \t+    (string) (len=4) \"Name\": (string) (len=25) \"iywbvukPXRwmdzNfLGEbjCcFE\",\n\t            \t+    (string) (len=6) \"UserID\": (float64) 94\n\t            \t+   },\n\t            \t+   (map[string]interface {}) (len=5) {\n\t            \t+    (string) (len=5) \"About\": (string) (len=25) \"DilxvBJzNwrQcrsVAuJdkFaNz\",\n\t            \t+    (string) (len=5) \"Color\": (string) (len=25) \"IyVKWsQDqUfyADWddPnuhRbyJ\",\n\t            \t+    (string) (len=2) \"ID\": (float64) 46,\n\t            \t+    (string) (len=4) \"Name\": (string) (len=25) \"gQoNzbRRLafHhDEwKtcqMlvif\",\n\t            \t+    (string) (len=6) \"UserID\": (float64) 57\n\t            \t+   },\n\t            \t+   (map[string]interface {}) (len=5) {\n\t            \t+    (string) (len=5) \"About\": (string) (len=25) \"BzXKpNiYEMfQsmpMBtwlDagmQ\",\n\t            \t+    (string) (len=5) \"Color\": (string) (len=25) \"gFgayYvtzMkGJDeEgOeOUtfmf\",\n\t            \t+    (string) (len=2) \"ID\": (float64) 40,\n\t            \t+    (string) (len=4) \"Name\": (string) (len=25) \"yTAkPWimHaNYCrHybsThPInyG\",\n\t            \t+    (string) (len=6) \"UserID\": (float64) 25\n\t            \t+   },\n\t            \t+   (map[string]interface {}) (len=5) {\n\t            \t+    (string) (len=5) \"About\": (string) (len=25) \"qpjLVSxtFDtNYkFWasVJWdkWS\",\n\t            \t+    (string) (len=5) \"Color\": (string) (len=25) \"OYXOqPuUcTpHBacrtyYrkVmJf\",\n\t            \t+    (string) (len=2) \"ID\": (float64) 97,\n\t            \t+    (string) (len=4) \"Name\": (string) (len=25) \"cXdtYjaPFRhYpXcFDIxwmWbwM\",\n\t            \t+    (string) (len=6) \"UserID\": (float64) 44\n\t            \t+   },\n\t            \t+   (map[string]interface {}) (len=5) {\n\t            \t+    (string) (len=5) \"About\": (string) (len=25) \"acqinUInZRwbgGSesFsXghAEc\",\n\t            \t+    (string) (len=5) \"Color\": (string) (len=25) \"zSYkDEHujMgtSWrbqsUzIgREX\",\n\t            \t+    (string) (len=2) \"ID\": (float64) 20,\n\t            \t+    (string) (len=4) \"Name\": (string) (len=25) \"FvNUdqLCPtzipNQQicbcrbRUU\",\n\t            \t+    (string) (len=6) \"UserID\": (float64) 99\n\t            \t+   },\n\t            \t+   (map[string]interface {}) (len=5) {\n\t            \t+    (string) (len=5) \"About\": (string) (len=25) \"kWAhVlghoDEfZLEXEaiOBfoha\",\n\t            \t+    (string) (len=5) \"Color\": (string) (len=25) \"CgZCNGWYZxHvWgyMASGehQgxK\",\n\t            \t+    (string) (len=2) \"ID\": (float64) 40,\n\t            \t+    (string) (len=4) \"Name\": (string) (len=25) \"oUkDRstEOAnfwrHZRskRzcjsG\",\n\t            \t+    (string) (len=6) \"UserID\": (float64) 24\n\t            \t+   },\n\t            \t+   (map[string]interface {}) (len=5) {\n\t            \t+    (string) (len=5) \"About\": (string) (len=25) \"MnRkAqCvJFtBieQBjraOulMFV\",\n\t            \t+    (string) (len=5) \"Color\": (string) (len=25) \"EkQojCOfPWbFDgYrbkSTnAFYg\",\n\t            \t+    (string) (len=2) \"ID\": (float64) 12,\n\t            \t+    (string) (len=4) \"Name\": (string) (len=25) \"vOqeiPsgidyMuygEwWpXkiRIO\",\n\t            \t+    (string) (len=6) \"UserID\": (float64) 79\n\t            \t+   },\n\t            \t+   (map[string]interface {}) (len=5) {\n\t            \t+    (string) (len=5) \"About\": (string) (len=25) \"eTmFfQqRjdtcERHQCFuHihspp\",\n\t            \t+    (string) (len=5) \"Color\": (string) (len=25) \"QLGMIwUSezmqTrgnkyetKoYgF\",\n\t            \t+    (string) (len=2) \"ID\": (float64) 7,\n\t            \t+    (string) (len=4) \"Name\": (string) (len=25) \"WGRmYFLLDTUKXZzsLDNWxTOhz\",\n\t            \t+    (string) (len=6) \"UserID\": (float64) 20\n\t            \t+   },\n\t            \t+   (map[string]interface {}) (len=5) {\n\t            \t+    (string) (len=5) \"About\": (string) (len=25) \"GNCUpxumMfaEVglXPoICthHxd\",\n\t            \t+    (string) (len=5) \"Color\": (string) (len=25) \"KwUhADqtyXGLRMYZGpfMgyMbp\",\n\t            \t+    (string) (len=2) \"ID\": (float64) 67,\n\t            \t+    (string) (len=4) \"Name\": (string) (len=25) \"DvkksZGiHwEzQTTSzikeCiJTE\",\n\t            \t+    (string) (len=6) \"UserID\": (float64) 43\n\t            \t+   },\n\t            \t+   (map[string]interface {}) (len=5) {\n\t            \t+    (string) (len=5) \"About\": (string) (len=25) \"DmFmkhqPOQWolwJSLVmPlwmyd\",\n\t            \t+    (string) (len=5) \"Color\": (string) (len=25) \"DpnBgkxFHmCmzujesUDtapiFf\",\n\t            \t+    (string) (len=2) \"ID\": (float64) 15,\n\t            \t+    (string) (len=4) \"Name\": (string) (len=25) \"xgsxspZZFiHqDBzTvuEmugpfT\",\n\t            \t+    (string) (len=6) \"UserID\": (float64) 95\n\t            \t+   },\n\t            \t+   (map[string]interface {}) (len=5) {\n\t            \t+    (string) (len=5) \"About\": (string) (len=25) \"WRPjsZQpFfmDTLfaEVAfvnZku\",\n\t            \t+    (string) (len=5) \"Color\": (string) (len=25) \"AMolqtClqCZlGYnbCgrZAEKYm\",\n\t            \t+    (string) (len=2) \"ID\": (float64) 47,\n\t            \t+    (string) (len=4) \"Name\": (string) (len=25) \"IORXqCjeJaIpNrxBgYuwNQEvs\",\n\t            \t+    (string) (len=6) \"UserID\": (float64) 61\n\t            \t+   },\n\t            \t+   (map[string]interface {}) (len=5) {\n\t            \t+    (string) (len=5) \"About\": (string) (len=25) \"cXIKhgwWusZWCYLGqOOyFFWZi\",\n\t            \t+    (string) (len=5) \"Color\": (string) (len=25) \"hOHFcCTUzCDkEuYhMTrzVMuOJ\",\n\t            \t+    (string) (len=2) \"ID\": (float64) 78,\n\t            \t+    (string) (len=4) \"Name\": (string) (len=25) \"BCwaAcTDohuDIxMyOmhDucDLJ\",\n\t            \t+    (string) (len=6) \"UserID\": (float64) 24\n\t            \t+   },\n\t            \t+   (map[string]interface {}) (len=5) {\n\t            \t+    (string) (len=5) \"About\": (string) (len=25) \"AJDvEGIVqHhWbfZLNlZCrakUV\",\n\t            \t+    (string) (len=5) \"Color\": (string) (len=25) \"gnxBrFmGFdfeCLtjoXbFnRnom\",\n\t            \t+    (string) (len=2) \"ID\": (float64) 32,\n\t            \t+    (string) (len=4) \"Name\": (string) (len=25) \"TUEsnkUvOvPmBzbrMVlHkJBgX\",\n\t            \t+    (string) (len=6) \"UserID\": (float64) 32\n\t            \t+   },\n\t            \t+   (map[string]interface {}) (len=5) {\n\t            \t+    (string) (len=5) \"About\": (string) (len=25) \"SlDaXdDQsaSzFJJEOqZRtIDWW\",\n\t            \t+    (string) (len=5) \"Color\": (string) (len=25) \"zotPbBCEWlZLzDphmCNwivMOD\",\n\t            \t+    (string) (len=2) \"ID\": (float64) 49,\n\t            \t+    (string) (len=4) \"Name\": (string) (len=25) \"zyKjsJpSbJZvEjQodffkbTQUn\",\n\t            \t+    (string) (len=6) \"UserID\": (float64) 65\n\t            \t+   },\n\t            \t+   (map[string]interface {}) (len=5) {\n\t            \t+    (string) (len=5) \"About\": (string) (len=25) \"AquvSfhZxaflPFCSNJcmgiOel\",\n\t            \t+    (string) (len=5) \"Color\": (string) (len=25) \"OhUAdxwYbaWoVaHKePmMVsQgn\",\n\t            \t+    (string) (len=2) \"ID\": (float64) 94,\n\t            \t+    (string) (len=4) \"Name\": (string) (len=25) \"YuZJAHgEQPYnblKXmFlLVJysV\",\n\t            \t+    (string) (len=6) \"UserID\": (float64) 40\n\t            \t+   },\n\t            \t+   (map[string]interface {}) (len=5) {\n\t            \t+    (string) (len=5) \"About\": (string) (len=25) \"zvxVoKyDtuiGpxneVMacnFgxB\",\n\t            \t+    (string) (len=5) \"Color\": (string) (len=25) \"NcygDnUtflioLfyXpntkpgZLO\",\n\t            \t+    (string) (len=2) \"ID\": (float64) 76,\n\t            \t+    (string) (len=4) \"Name\": (string) (len=25) \"OXgJnatcVWGOKgbfYnJqQwtaC\",\n\t            \t+    (string) (len=6) \"UserID\": (float64) 67\n\t            \t+   },\n\t            \t+   (map[string]interface {}) (len=5) {\n\t            \t+    (string) (len=5) \"About\": (string) (len=25) \"mYDEdCGKyBgGWNrgQcWiWmdOB\",\n\t            \t+    (string) (len=5) \"Color\": (string) (len=25) \"GexziBOwmXfzIywMgAqMzGuiU\",\n\t            \t+    (string) (len=2) \"ID\": (float64) 1,\n\t            \t+    (string) (len=4) \"Name\": (string) (len=25) \"EvZEOKGSNYcNuIIjykArugpuQ\",\n\t            \t+    (string) (len=6) \"UserID\": (float64) 7\n\t            \t+   },\n\t            \t+   (map[string]interface {}) (len=5) {\n\t            \t+    (string) (len=5) \"About\": (string) (len=25) \"tEbxklfeiLroOVdlzTJwsielG\",\n\t            \t+    (string) (len=5) \"Color\": (string) (len=25) \"ogdUsEwqJplBPxGFRSVdDiOHs\",\n\t            \t+    (string) (len=2) \"ID\": (float64) 77,\n\t            \t+    (string) (len=4) \"Name\": (string) (len=25) \"dKFdfLMQMzGLsorUDHBYatadh\",\n\t            \t+    (string) (len=6) \"UserID\": (float64) 26\n\t            \t+   },\n\t            \t+   (map[string]interface {}) (len=5) {\n\t            \t+    (string) (len=5) \"About\": (string) (len=25) \"lMMWdqjHgXtkHSyJhQdLDxOQA\",\n\t            \t+    (string) (len=5) \"Color\": (string) (len=25) \"VmadUrsyLJATgaaiJJeoRaljZ\",\n\t            \t+    (string) (len=2) \"ID\": (float64) 37,\n\t            \t+    (string) (len=4) \"Name\": (string) (len=25) \"IDDlbPXVMEaffnUkutJWpWSnM\",\n\t            \t+    (string) (len=6) \"UserID\": (float64) 1\n\t            \t+   },\n\t            \t+   (map[string]interface {}) (len=5) {\n\t            \t+    (string) (len=5) \"About\": (string) (len=25) \"DrMzDVcvHCtSGpyBGjndfZKMk\",\n\t            \t+    (string) (len=5) \"Color\": (string) (len=25) \"MJvLBgcnbtDgGlcIZZtcQTTtg\",\n\t            \t+    (string) (len=2) \"ID\": (float64) 16,\n\t            \t+    (string) (len=4) \"Name\": (string) (len=25) \"PmVXaBnYHUOOheTcRfYahjzOw\",\n\t            \t+    (string) (len=6) \"UserID\": (float64) 45\n\t            \t+   },\n\t            \t+   (map[string]interface {}) (len=5) {\n\t            \t+    (string) (len=5) \"About\": (string) (len=25) \"CTOCExlWuAHBZWxnIPrUpprPJ\",\n\t            \t+    (string) (len=5) \"Color\": (string) (len=25) \"tPKlAuMZbronlMkLAwVLSAfrG\",\n\t            \t+    (string) (len=2) \"ID\": (float64) 50,\n\t            \t+    (string) (len=4) \"Name\": (string) (len=25) \"VmSoqHzpmpZNxlnFtXFCgcHXa\",\n\t            \t+    (string) (len=6) \"UserID\": (float64) 45\n\t            \t+   },\n\t            \t+   (map[string]interface {}) (len=5) {\n\t            \t+    (string) (len=5) \"About\": (string) (len=25) \"wMsytEGWQCPNvBxGaNSGLgFuW\",\n\t            \t+    (string) (len=5) \"Color\": (string) (len=25) \"VSMOZXFDMdvPrfCFRQahZpeJi\",\n\t            \t+    (string) (len=2) \"ID\": (float64) 0,\n\t            \t+    (string) (len=4) \"Name\": (string) (len=25) \"byrCrWITDlCOUQFwbKASqqYOk\",\n\t            \t+    (string) (len=6) \"UserID\": (float64) 49\n\t            \t+   },\n\t            \t+   (map[string]interface {}) (len=5) {\n\t            \t+    (string) (len=5) \"About\": (string) (len=25) \"FVjtOcDFenwnPasNYArYiFJpU\",\n\t            \t+    (string) (len=5) \"Color\": (string) (len=25) \"lhIXdvKsAKTNHFPsCMmxaJcAw\",\n\t            \t+    (string) (len=2) \"ID\": (float64) 25,\n\t            \t+    (string) (len=4) \"Name\": (string) (len=25) \"puMZYvHrxpIgjALTadDknWeHb\",\n\t            \t+    (string) (len=6) \"UserID\": (float64) 41\n\t            \t+   },\n\t            \t+   (map[string]interface {}) (len=5) {\n\t            \t+    (string) (len=5) \"About\": (string) (len=25) \"MmZafZzDdbGQSNzCqhsDwFXcQ\",\n\t            \t+    (string) (len=5) \"Color\": (string) (len=25) \"zxoPtEzvPMdNMHmdDFvibSaUr\",\n\t            \t+    (string) (len=2) \"ID\": (float64) 90,\n\t            \t+    (string) (len=4) \"Name\": (string) (len=25) \"DYrbyUgUerxmPnucvyodadTkJ\",\n\t            \t+    (string) (len=6) \"UserID\": (float64) 21\n\t            \t+   },\n\t            \t+   (map[string]interface {}) (len=5) {\n\t            \t+    (string) (len=5) \"About\": (string) (len=25) \"hLzmfGogKYewiypMDSpCRGHkB\",\n\t            \t+    (string) (len=5) \"Color\": (string) (len=25) \"mcRSfXgNjLXPvrAfBRAmdANIT\",\n\t            \t+    (string) (len=2) \"ID\": (float64) 50,\n\t            \t+    (string) (len=4) \"Name\": (string) (len=25) \"FXvTbVTbKZxZYyMlULROLjXtP\",\n\t            \t+    (string) (len=6) \"UserID\": (float64) 24\n\t            \t+   },\n\t            \t+   (map[string]interface {}) (len=5) {\n\t            \t+    (string) (len=5) \"About\": (string) (len=25) \"EOBkDlbBmbGioyUGhSSxTKonk\",\n\t            \t+    (string) (len=5) \"Color\": (string) (len=25) \"dIborAbaRFLPzWQYpigfCLTtc\",\n\t            \t+    (string) (len=2) \"ID\": (float64) 49,\n\t            \t+    (string) (len=4) \"Name\": (string) (len=25) \"HoOMKKsZEOuTcHNbpRjfQkkJo\",\n\t            \t+    (string) (len=6) \"UserID\": (float64) 86\n\t            \t+   },\n\t            \t+   (map[string]interface {}) (len=5) {\n\t            \t+    (string) (len=5) \"About\": (string) (len=25) \"sJpEnQWROhvzZTGVJJrVdlxqz\",\n\t            \t+    (string) (len=5) \"Color\": (string) (len=25) \"xMSlwufhrbeAQDmKlzWpwOfqY\",\n\t            \t+    (string) (len=2) \"ID\": (float64) 2,\n\t            \t+    (string) (len=4) \"Name\": (string) (len=25) \"EhZgAqSVPkOWvtvDHkvwBoBxh\",\n\t            \t+    (string) (len=6) \"UserID\": (float64) 47\n\t            \t+   },\n\t            \t+   (map[string]interface {}) (len=5) {\n\t            \t+    (string) (len=5) \"About\": (string) (len=25) \"NmNhSwYoMCSFjxwSDuySwYJRT\",\n\t            \t+    (string) (len=5) \"Color\": (string) (len=25) \"HYIqFwIhYpMEsvyacmfXtVdSX\",\n\t            \t+    (string) (len=2) \"ID\": (float64) 83,\n\t            \t+    (string) (len=4) \"Name\": (string) (len=25) \"bKtaMKaTohdQxOIQLgmUETLGR\",\n\t            \t+    (string) (len=6) \"UserID\": (float64) 77\n\t            \t+   },\n\t            \t+   (map[string]interface {}) (len=5) {\n\t            \t+    (string) (len=5) \"About\": (string) (len=25) \"qDhMtHxFIaZdJdVyzIpYFucto\",\n\t            \t+    (string) (len=5) \"Color\": (string) (len=25) \"JIkjyoJMBAKKEcYqBFbzMeGDR\",\n\t            \t+    (string) (len=2) \"ID\": (float64) 43,\n\t            \t+    (string) (len=4) \"Name\": (string) (len=25) \"GcvmNdJsISAWPzkdZlgpCgPyk\",\n\t            \t+    (string) (len=6) \"UserID\": (float64) 1\n\t            \t+   },\n\t            \t+   (map[string]interface {}) (len=5) {\n\t            \t+    (string) (len=5) \"About\": (string) (len=25) \"pqggXcQFpGkKIjOHWdxcbRXsK\",\n\t            \t+    (string) (len=5) \"Color\": (string) (len=25) \"GWaEMvJiqbieQZZMydQPhTvAn\",\n\t            \t+    (string) (len=2) \"ID\": (float64) 92,\n\t            \t+    (string) (len=4) \"Name\": (string) (len=25) \"rWOKoHdNkAYnkcXFerycGXZaF\",\n\t            \t+    (string) (len=6) \"UserID\": (float64) 3\n\t            \t+   },\n\t            \t+   (map[string]interface {}) (len=5) {\n\t            \t+    (string) (len=5) \"About\": (string) (len=25) \"wbdPZNEMnOXKLgKQruVHyTNtp\",\n\t            \t+    (string) (len=5) \"Color\": (string) (len=25) \"jkApwbrepJccNGaOGHpuwlwxZ\",\n\t            \t+    (string) (len=2) \"ID\": (float64) 76,\n\t            \t+    (string) (len=4) \"Name\": (string) (len=25) \"rYxYUhOUuguQZqTGxLMovzUtH\",\n\t            \t+    (string) (len=6) \"UserID\": (float64) 24\n\t            \t+   },\n\t            \t+   (map[string]interface {}) (len=5) {\n\t            \t+    (string) (len=5) \"About\": (string) (len=25) \"jeXqLWSuNDPdCsvLHnoLCkBFV\",\n\t            \t+    (string) (len=5) \"Color\": (string) (len=25) \"UAOnqfkPdPKHlnScjkwYrjKYr\",\n\t            \t+    (string) (len=2) \"ID\": (float64) 19,\n\t            \t+    (string) (len=4) \"Name\": (string) (len=25) \"COdgBIzxaQlZglRoCqJiVxTAk\",\n\t            \t+    (string) (len=6) \"UserID\": (float64) 92\n\t            \t+   },\n\t            \t+   (map[string]interface {}) (len=5) {\n\t            \t+    (string) (len=5) \"About\": (string) (len=25) \"hANgjWfWkQjvsoURboarADLzk\",\n\t            \t+    (string) (len=5) \"Color\": (string) (len=25) \"tBwqKNsZZLkQWBnQEEkcIAaqw\",\n\t            \t+    (string) (len=2) \"ID\": (float64) 2,\n\t            \t+    (string) (len=4) \"Name\": (string) (len=25) \"TgjgyXcVLoIsDeGLppkrulGpV\",\n\t            \t+    (string) (len=6) \"UserID\": (float64) 43\n\t            \t+   },\n\t            \t+   (map[string]interface {}) (len=5) {\n\t            \t+    (string) (len=5) \"About\": (string) (len=25) \"LoExNLuhTtBmvhzrzVkNucnjl\",\n\t            \t+    (string) (len=5) \"Color\": (string) (len=25) \"ebuihoQwqZxFcltmvLESjovGx\",\n\t            \t+    (string) (len=2) \"ID\": (float64) 96,\n\t            \t+    (string) (len=4) \"Name\": (string) (len=25) \"sUNUHYwhTYFhoSBKlpTvItxjS\",\n\t            \t+    (string) (len=6) \"UserID\": (float64) 48\n\t            \t+   },\n\t            \t+   (map[string]interface {}) (len=5) {\n\t            \t+    (string) (len=5) \"About\": (string) (len=25) \"XZJqlcwNAJUShGxmmTgDYZaHy\",\n\t            \t+    (string) (len=5) \"Color\": (string) (len=25) \"nxWXWgsnTFMIWqdleGjsKOGHD\",\n\t            \t+    (string) (len=2) \"ID\": (float64) 55,\n\t            \t+    (string) (len=4) \"Name\": (string) (len=25) \"WouGVQxDMxnYKSLVApdbhaqTp\",\n\t            \t+    (string) (len=6) \"UserID\": (float64) 57\n\t            \t+   },\n\t            \t+   (map[string]interface {}) (len=5) {\n\t            \t+    (string) (len=5) \"About\": (string) (len=25) \"rZVdfehCwPhekZRRVZCnTRtIn\",\n\t            \t+    (string) (len=5) \"Color\": (string) (len=25) \"ysjddhhTdvDcRgGshOhuyWTDc\",\n\t            \t+    (string) (len=2) \"ID\": (float64) 16,\n\t            \t+    (string) (len=4) \"Name\": (string) (len=25) \"miUIIuhwiXCsttHuJWWoXDuCz\",\n\t            \t+    (string) (len=6) \"UserID\": (float64) 76\n\t            \t+   },\n\t            \t+   (map[string]interface {}) (len=5) {\n\t            \t+    (string) (len=5) \"About\": (string) (len=25) \"uGHkiFXWCqiBKNsyStqZJhsSh\",\n\t            \t+    (string) (len=5) \"Color\": (string) (len=25) \"YCpCayxilRbnTdujYuKrMOGYl\",\n\t            \t+    (string) (len=2) \"ID\": (float64) 76,\n\t            \t+    (string) (len=4) \"Name\": (string) (len=25) \"pELHXvATHBSOUCyvfmyNaSBbW\",\n\t            \t+    (string) (len=6) \"UserID\": (float64) 93\n\t            \t+   },\n\t            \t+   (map[string]interface {}) (len=5) {\n\t            \t+    (string) (len=5) \"About\": (string) (len=25) \"wwYjjCyvwDSMnAQxmQBdTeYRd\",\n\t            \t+    (string) (len=5) \"Color\": (string) (len=25) \"eCWtnvWmkUxGzHsfrRHRDoJyx\",\n\t            \t+    (string) (len=2) \"ID\": (float64) 94,\n\t            \t+    (string) (len=4) \"Name\": (string) (len=25) \"ZUforRAvxSBwdZisqmGyQHGoG\",\n\t            \t+    (string) (len=6) \"UserID\": (float64) 30\n\t            \t+   },\n\t            \t+   (map[string]interface {}) (len=5) {\n\t            \t+    (string) (len=5) \"About\": (string) (len=25) \"xyfDfcYBYssSORvmikhSLcuyG\",\n\t            \t+    (string) (len=5) \"Color\": (string) (len=25) \"eoGoZAtKQnczfPPWPughOSEgI\",\n\t            \t+    (string) (len=2) \"ID\": (float64) 53,\n\t            \t+    (string) (len=4) \"Name\": (string) (len=25) \"dmsWUCgBIjUSvnekgeoqrXKYR\",\n\t            \t+    (string) (len=6) \"UserID\": (float64) 80\n\t            \t+   },\n\t            \t+   (map[string]interface {}) (len=5) {\n\t            \t+    (string) (len=5) \"About\": (string) (len=25) \"pQiOOONtbVaSQwMoyybWuoVBz\",\n\t            \t+    (string) (len=5) \"Color\": (string) (len=25) \"rgGhWzoaJRmxhLisvqgTuDJXz\",\n\t            \t+    (string) (len=2) \"ID\": (float64) 4,\n\t            \t+    (string) (len=4) \"Name\": (string) (len=25) \"NSuXYKfilgvHBDWzCBiFQVwWf\",\n\t            \t+    (string) (len=6) \"UserID\": (float64) 49\n\t            \t+   },\n\t            \t+   (map[string]interface {}) (len=5) {\n\t            \t+    (string) (len=5) \"About\": (string) (len=25) \"gfgbOxyMNTFzuZLMcneczCMTu\",\n\t            \t+    (string) (len=5) \"Color\": (string) (len=25) \"GdvXJhxUsHarvZdDyGjjcjErO\",\n\t            \t+    (string) (len=2) \"ID\": (float64) 10,\n\t            \t+    (string) (len=4) \"Name\": (string) (len=25) \"MpPcxFPsApIbTGpMLzoUzHFvW\",\n\t            \t+    (string) (len=6) \"UserID\": (float64) 74\n\t            \t+   },\n\t            \t+   (map[string]interface {}) (len=5) {\n\t            \t+    (string) (len=5) \"About\": (string) (len=25) \"ekoFctoxzNVzioSuGZZdbZUnw\",\n\t            \t+    (string) (len=5) \"Color\": (string) (len=25) \"sUtfNMwwIofrigIiCSoxCfmbH\",\n\t            \t+    (string) (len=2) \"ID\": (float64) 76,\n\t            \t+    (string) (len=4) \"Name\": (string) (len=25) \"hyliSrckXcoKArloyQdEWRsSs\",\n\t            \t+    (string) (len=6) \"UserID\": (float64) 15\n\t            \t+   },\n\t            \t+   (map[string]interface {}) (len=5) {\n\t            \t+    (string) (len=5) \"About\": (string) (len=25) \"lJZMuuGEdElVCrXvchuwqGbPj\",\n\t            \t+    (string) (len=5) \"Color\": (string) (len=25) \"JUxogvLyZphBaQzTrEcAMyBYO\",\n\t            \t+    (string) (len=2) \"ID\": (float64) 15,\n\t            \t+    (string) (len=4) \"Name\": (string) (len=25) \"dXmulEWSOYVSeFrFQjBpKpIhz\",\n\t            \t+    (string) (len=6) \"UserID\": (float64) 88\n\t            \t+   },\n\t            \t+   (map[string]interface {}) (len=5) {\n\t            \t+    (string) (len=5) \"About\": (string) (len=25) \"rkcSpIysBucfWbEQMLMhXiAmA\",\n\t            \t+    (string) (len=5) \"Color\": (string) (len=25) \"uKAudzmrtlOwzNaMicBfGULoR\",\n\t            \t+    (string) (len=2) \"ID\": (float64) 10,\n\t            \t+    (string) (len=4) \"Name\": (string) (len=25) \"wVWjzEbVxqPKMtYuPTLvZgNFy\",\n\t            \t+    (string) (len=6) \"UserID\": (float64) 34\n\t            \t+   },\n\t            \t+   (map[string]interface {}) (len=5) {\n\t            \t+    (string) (len=5) \"About\": (string) (len=25) \"JcsKTqdUgGkdSqUjVdFioMYCO\",\n\t            \t+    (string) (len=5) \"Color\": (string) (len=25) \"SINnkFDYIDFWolYjzSpfflrHe\",\n\t            \t+    (string) (len=2) \"ID\": (float64) 33,\n\t            \t+    (string) (len=4) \"Name\": (string) (len=25) \"zzAgmHRnBOgaqCFvZSAqrdedD\",\n\t            \t+    (string) (len=6) \"UserID\": (float64) 81\n\t            \t+   },\n\t            \t+   (map[string]interface {}) (len=5) {\n\t            \t+    (string) (len=5) \"About\": (string) (len=25) \"VOnBZXtRtAVADUktahQrGXrBM\",\n\t            \t+    (string) (len=5) \"Color\": (string) (len=25) \"HuoEzfLlpJDtRPhTGLpMBKCzC\",\n\t            \t+    (string) (len=2) \"ID\": (float64) 2,\n\t            \t+    (string) (len=4) \"Name\": (string) (len=25) \"BaXSywAdJczPtnNJZxilsBwxw\",\n\t            \t+    (string) (len=6) \"UserID\": (float64) 11\n\t            \t+   },\n\t            \t+   (map[string]interface {}) (len=5) {\n\t            \t+    (string) (len=5) \"About\": (string) (len=25) \"dMOFhZBKiTJHsFkvjDsmxCGYK\",\n\t            \t+    (string) (len=5) \"Color\": (string) (len=25) \"WOEiZGVbIWZWunzJBKGBQdwfV\",\n\t            \t+    (string) (len=2) \"ID\": (float64) 44,\n\t            \t+    (string) (len=4) \"Name\": (string) (len=25) \"aBxOyAkeLPfzYNJDuhkTjUdPz\",\n\t            \t+    (string) (len=6) \"UserID\": (float64) 75\n\t            \t+   }\n\t            \t   },\n","trace":"\n\n\tError Trace:\t/Users/d.neumoin/go/pkg/mod/github.com/ozontech/allure-go/pkg/framework@v0.6.28/asserts_wrapper/wrapper/wrapper.go:512\n\t            \t\t\t\t/Users/d.neumoin/go/pkg/mod/github.com/ozontech/allure-go/pkg/framework@v0.6.28/asserts_wrapper/wrapper/helper.go:37\n\t            \t\t\t\t/Users/d.neumoin/go/pkg/mod/github.com/ozontech/allure-go/pkg/framework@v0.6.28/asserts_wrapper/wrapper/wrapper.go:508\n\t            \t\t\t\t/Users/d.neumoin/go/pkg/mod/github.com/ozontech/allure-go/pkg/framework@v0.6.28/asserts_wrapper/helper/helper.go:142\n\t            \t\t\t\t/Users/d.neumoin/iu7-test/src/integration_test/delivery_usecase/entry_test.go:247\n\tError:      \tNot equal: \n\t            \texpected: map[string]interface {}{\"body\":map[string]interface {}{\"description\":\"entry\", \"duration\":\"2h0m0s\", \"id\":1, \"project_id\":interface {}(nil), \"tag_list\":[]interface {}{}, \"time_end\":\"2021-08-15T16:30:45+03:00\", \"time_start\":\"2021-08-15T14:30:45+03:00\", \"user_id\":1}}\n\t            \tactual  : map[string]interface {}{\"body\":map[string]interface {}{\"description\":\"entry\", \"duration\":\"2h0m0s\", \"id\":1, \"project_id\":interface {}(nil), \"tag_list\":[]interface {}{map[string]interface {}{\"About\":\"FBqdwkwpYncTYQgwhMnyUqtei\", \"Color\":\"SSindaNAHWEkBukErBsoXNSAX\", \"ID\":60, \"Name\":\"kykZXjMpnPxCRdHHUlOIKlOEC\", \"UserID\":8}, map[string]interface {}{\"About\":\"DQlDzkeQJScLPIwpwDrcRMknE\", \"Color\":\"AhxrXMmRSdbIeAywJQMXeKxxT\", \"ID\":1, \"Name\":\"iywbvukPXRwmdzNfLGEbjCcFE\", \"UserID\":94}, map[string]interface {}{\"About\":\"DilxvBJzNwrQcrsVAuJdkFaNz\", \"Color\":\"IyVKWsQDqUfyADWddPnuhRbyJ\", \"ID\":46, \"Name\":\"gQoNzbRRLafHhDEwKtcqMlvif\", \"UserID\":57}, map[string]interface {}{\"About\":\"BzXKpNiYEMfQsmpMBtwlDagmQ\", \"Color\":\"gFgayYvtzMkGJDeEgOeOUtfmf\", \"ID\":40, \"Name\":\"yTAkPWimHaNYCrHybsThPInyG\", \"UserID\":25}, map[string]interface {}{\"About\":\"qpjLVSxtFDtNYkFWasVJWdkWS\", \"Color\":\"OYXOqPuUcTpHBacrtyYrkVmJf\", \"ID\":97, \"Name\":\"cXdtYjaPFRhYpXcFDIxwmWbwM\", \"UserID\":44}, map[string]interface {}{\"About\":\"acqinUInZRwbgGSesFsXghAEc\", \"Color\":\"zSYkDEHujMgtSWrbqsUzIgREX\", \"ID\":20, \"Name\":\"FvNUdqLCPtzipNQQicbcrbRUU\", \"UserID\":99}, map[string]interface {}{\"About\":\"kWAhVlghoDEfZLEXEaiOBfoha\", \"Color\":\"CgZCNGWYZxHvWgyMASGehQgxK\", \"ID\":40, \"Name\":\"oUkDRstEOAnfwrHZRskRzcjsG\", \"UserID\":24}, map[string]interface {}{\"About\":\"MnRkAqCvJFtBieQBjraOulMFV\", \"Color\":\"EkQojCOfPWbFDgYrbkSTnAFYg\", \"ID\":12, \"Name\":\"vOqeiPsgidyMuygEwWpXkiRIO\", \"UserID\":79}, map[string]interface {}{\"About\":\"eTmFfQqRjdtcERHQCFuHihspp\", \"Color\":\"QLGMIwUSezmqTrgnkyetKoYgF\", \"ID\":7, \"Name\":\"WGRmYFLLDTUKXZzsLDNWxTOhz\", \"UserID\":20}, map[string]interface {}{\"About\":\"GNCUpxumMfaEVglXPoICthHxd\", \"Color\":\"KwUhADqtyXGLRMYZGpfMgyMbp\", \"ID\":67, \"Name\":\"DvkksZGiHwEzQTTSzikeCiJTE\", \"UserID\":43}, map[string]interface {}{\"About\":\"DmFmkhqPOQWolwJSLVmPlwmyd\", \"Color\":\"DpnBgkxFHmCmzujesUDtapiFf\", \"ID\":15, \"Name\":\"xgsxspZZFiHqDBzTvuEmugpfT\", \"UserID\":95}, map[string]interface {}{\"About\":\"WRPjsZQpFfmDTLfaEVAfvnZku\", \"Color\":\"AMolqtClqCZlGYnbCgrZAEKYm\", \"ID\":47, \"Name\":\"IORXqCjeJaIpNrxBgYuwNQEvs\", \"UserID\":61}, map[string]interface {}{\"About\":\"cXIKhgwWusZWCYLGqOOyFFWZi\", \"Color\":\"hOHFcCTUzCDkEuYhMTrzVMuOJ\", \"ID\":78, \"Name\":\"BCwaAcTDohuDIxMyOmhDucDLJ\", \"UserID\":24}, map[string]interface {}{\"About\":\"AJDvEGIVqHhWbfZLNlZCrakUV\", \"Color\":\"gnxBrFmGFdfeCLtjoXbFnRnom\", \"ID\":32, \"Name\":\"TUEsnkUvOvPmBzbrMVlHkJBgX\", \"UserID\":32}, map[string]interface {}{\"About\":\"SlDaXdDQsaSzFJJEOqZRtIDWW\", \"Color\":\"zotPbBCEWlZLzDphmCNwivMOD\", \"ID\":49, \"Name\":\"zyKjsJpSbJZvEjQodffkbTQUn\", \"UserID\":65}, map[string]interface {}{\"About\":\"AquvSfhZxaflPFCSNJcmgiOel\", \"Color\":\"OhUAdxwYbaWoVaHKePmMVsQgn\", \"ID\":94, \"Name\":\"YuZJAHgEQPYnblKXmFlLVJysV\", \"UserID\":40}, map[string]interface {}{\"About\":\"zvxVoKyDtuiGpxneVMacnFgxB\", \"Color\":\"NcygDnUtflioLfyXpntkpgZLO\", \"ID\":76, \"Name\":\"OXgJnatcVWGOKgbfYnJqQwtaC\", \"UserID\":67}, map[string]interface {}{\"About\":\"mYDEdCGKyBgGWNrgQcWiWmdOB\", \"Color\":\"GexziBOwmXfzIywMgAqMzGuiU\", \"ID\":1, \"Name\":\"EvZEOKGSNYcNuIIjykArugpuQ\", \"UserID\":7}, map[string]interface {}{\"About\":\"tEbxklfeiLroOVdlzTJwsielG\", \"Color\":\"ogdUsEwqJplBPxGFRSVdDiOHs\", \"ID\":77, \"Name\":\"dKFdfLMQMzGLsorUDHBYatadh\", \"UserID\":26}, map[string]interface {}{\"About\":\"lMMWdqjHgXtkHSyJhQdLDxOQA\", \"Color\":\"VmadUrsyLJATgaaiJJeoRaljZ\", \"ID\":37, \"Name\":\"IDDlbPXVMEaffnUkutJWpWSnM\", \"UserID\":1}, map[string]interface {}{\"About\":\"DrMzDVcvHCtSGpyBGjndfZKMk\", \"Color\":\"MJvLBgcnbtDgGlcIZZtcQTTtg\", \"ID\":16, \"Name\":\"PmVXaBnYHUOOheTcRfYahjzOw\", \"UserID\":45}, map[string]interface {}{\"About\":\"CTOCExlWuAHBZWxnIPrUpprPJ\", \"Color\":\"tPKlAuMZbronlMkLAwVLSAfrG\", \"ID\":50, \"Name\":\"VmSoqHzpmpZNxlnFtXFCgcHXa\", \"UserID\":45}, map[string]interface {}{\"About\":\"wMsytEGWQCPNvBxGaNSGLgFuW\", \"Color\":\"VSMOZXFDMdvPrfCFRQahZpeJi\", \"ID\":0, \"Name\":\"byrCrWITDlCOUQFwbKASqqYOk\", \"UserID\":49}, map[string]interface {}{\"About\":\"FVjtOcDFenwnPasNYArYiFJpU\", \"Color\":\"lhIXdvKsAKTNHFPsCMmxaJcAw\", \"ID\":25, \"Name\":\"puMZYvHrxpIgjALTadDknWeHb\", \"UserID\":41}, map[string]interface {}{\"About\":\"MmZafZzDdbGQSNzCqhsDwFXcQ\", \"Color\":\"zxoPtEzvPMdNMHmdDFvibSaUr\", \"ID\":90, \"Name\":\"DYrbyUgUerxmPnucvyodadTkJ\", \"UserID\":21}, map[string]interface {}{\"About\":\"hLzmfGogKYewiypMDSpCRGHkB\", \"Color\":\"mcRSfXgNjLXPvrAfBRAmdANIT\", \"ID\":50, \"Name\":\"FXvTbVTbKZxZYyMlULROLjXtP\", \"UserID\":24}, map[string]interface {}{\"About\":\"EOBkDlbBmbGioyUGhSSxTKonk\", \"Color\":\"dIborAbaRFLPzWQYpigfCLTtc\", \"ID\":49, \"Name\":\"HoOMKKsZEOuTcHNbpRjfQkkJo\", \"UserID\":86}, map[string]interface {}{\"About\":\"sJpEnQWROhvzZTGVJJrVdlxqz\", \"Color\":\"xMSlwufhrbeAQDmKlzWpwOfqY\", \"ID\":2, \"Name\":\"EhZgAqSVPkOWvtvDHkvwBoBxh\", \"UserID\":47}, map[string]interface {}{\"About\":\"NmNhSwYoMCSFjxwSDuySwYJRT\", \"Color\":\"HYIqFwIhYpMEsvyacmfXtVdSX\", \"ID\":83, \"Name\":\"bKtaMKaTohdQxOIQLgmUETLGR\", \"UserID\":77}, map[string]interface {}{\"About\":\"qDhMtHxFIaZdJdVyzIpYFucto\", \"Color\":\"JIkjyoJMBAKKEcYqBFbzMeGDR\", \"ID\":43, \"Name\":\"GcvmNdJsISAWPzkdZlgpCgPyk\", \"UserID\":1}, map[string]interface {}{\"About\":\"pqggXcQFpGkKIjOHWdxcbRXsK\", \"Color\":\"GWaEMvJiqbieQZZMydQPhTvAn\", \"ID\":92, \"Name\":\"rWOKoHdNkAYnkcXFerycGXZaF\", \"UserID\":3}, map[string]interface {}{\"About\":\"wbdPZNEMnOXKLgKQruVHyTNtp\", \"Color\":\"jkApwbrepJccNGaOGHpuwlwxZ\", \"ID\":76, \"Name\":\"rYxYUhOUuguQZqTGxLMovzUtH\", \"UserID\":24}, map[string]interface {}{\"About\":\"jeXqLWSuNDPdCsvLHnoLCkBFV\", \"Color\":\"UAOnqfkPdPKHlnScjkwYrjKYr\", \"ID\":19, \"Name\":\"COdgBIzxaQlZglRoCqJiVxTAk\", \"UserID\":92}, map[string]interface {}{\"About\":\"hANgjWfWkQjvsoURboarADLzk\", \"Color\":\"tBwqKNsZZLkQWBnQEEkcIAaqw\", \"ID\":2, \"Name\":\"TgjgyXcVLoIsDeGLppkrulGpV\", \"UserID\":43}, map[string]interface {}{\"About\":\"LoExNLuhTtBmvhzrzVkNucnjl\", \"Color\":\"ebuihoQwqZxFcltmvLESjovGx\", \"ID\":96, \"Name\":\"sUNUHYwhTYFhoSBKlpTvItxjS\", \"UserID\":48}, map[string]interface {}{\"About\":\"XZJqlcwNAJUShGxmmTgDYZaHy\", \"Color\":\"nxWXWgsnTFMIWqdleGjsKOGHD\", \"ID\":55, \"Name\":\"WouGVQxDMxnYKSLVApdbhaqTp\", \"UserID\":57}, map[string]interface {}{\"About\":\"rZVdfehCwPhekZRRVZCnTRtIn\", \"Color\":\"ysjddhhTdvDcRgGshOhuyWTDc\", \"ID\":16, \"Name\":\"miUIIuhwiXCsttHuJWWoXDuCz\", \"UserID\":76}, map[string]interface {}{\"About\":\"uGHkiFXWCqiBKNsyStqZJhsSh\", \"Color\":\"YCpCayxilRbnTdujYuKrMOGYl\", \"ID\":76, \"Name\":\"pELHXvATHBSOUCyvfmyNaSBbW\", \"UserID\":93}, map[string]interface {}{\"About\":\"wwYjjCyvwDSMnAQxmQBdTeYRd\", \"Color\":\"eCWtnvWmkUxGzHsfrRHRDoJyx\", \"ID\":94, \"Name\":\"ZUforRAvxSBwdZisqmGyQHGoG\", \"UserID\":30}, map[string]interface {}{\"About\":\"xyfDfcYBYssSORvmikhSLcuyG\", \"Color\":\"eoGoZAtKQnczfPPWPughOSEgI\", \"ID\":53, \"Name\":\"dmsWUCgBIjUSvnekgeoqrXKYR\", \"UserID\":80}, map[string]interface {}{\"About\":\"pQiOOONtbVaSQwMoyybWuoVBz\", \"Color\":\"rgGhWzoaJRmxhLisvqgTuDJXz\", \"ID\":4, \"Name\":\"NSuXYKfilgvHBDWzCBiFQVwWf\", \"UserID\":49}, map[string]interface {}{\"About\":\"gfgbOxyMNTFzuZLMcneczCMTu\", \"Color\":\"GdvXJhxUsHarvZdDyGjjcjErO\", \"ID\":10, \"Name\":\"MpPcxFPsApIbTGpMLzoUzHFvW\", \"UserID\":74}, map[string]interface {}{\"About\":\"ekoFctoxzNVzioSuGZZdbZUnw\", \"Color\":\"sUtfNMwwIofrigIiCSoxCfmbH\", \"ID\":76, \"Name\":\"hyliSrckXcoKArloyQdEWRsSs\", \"UserID\":15}, map[string]interface {}{\"About\":\"lJZMuuGEdElVCrXvchuwqGbPj\", \"Color\":\"JUxogvLyZphBaQzTrEcAMyBYO\", \"ID\":15, \"Name\":\"dXmulEWSOYVSeFrFQjBpKpIhz\", \"UserID\":88}, map[string]interface {}{\"About\":\"rkcSpIysBucfWbEQMLMhXiAmA\", \"Color\":\"uKAudzmrtlOwzNaMicBfGULoR\", \"ID\":10, \"Name\":\"wVWjzEbVxqPKMtYuPTLvZgNFy\", \"UserID\":34}, map[string]interface {}{\"About\":\"JcsKTqdUgGkdSqUjVdFioMYCO\", \"Color\":\"SINnkFDYIDFWolYjzSpfflrHe\", \"ID\":33, \"Name\":\"zzAgmHRnBOgaqCFvZSAqrdedD\", \"UserID\":81}, map[string]interface {}{\"About\":\"VOnBZXtRtAVADUktahQrGXrBM\", \"Color\":\"HuoEzfLlpJDtRPhTGLpMBKCzC\", \"ID\":2, \"Name\":\"BaXSywAdJczPtnNJZxilsBwxw\", \"UserID\":11}, map[string]interface {}{\"About\":\"dMOFhZBKiTJHsFkvjDsmxCGYK\", \"Color\":\"WOEiZGVbIWZWunzJBKGBQdwfV\", \"ID\":44, \"Name\":\"aBxOyAkeLPfzYNJDuhkTjUdPz\", \"UserID\":75}}, \"time_end\":\"2021-08-15T16:30:45+03:00\", \"time_start\":\"2021-08-15T14:30:45+03:00\", \"user_id\":1}}\n\t            \t\n\t            \tDiff:\n\t            \t--- Expected\n\t            \t+++ Actual\n\t            \t@@ -6,3 +6,339 @@\n\t            \t   (string) (len=10) \"project_id\": (interface {}) \u003cnil\u003e,\n\t            \t-  (string) (len=8) \"tag_list\": ([]interface {}) {\n\t            \t+  (string) (len=8) \"tag_list\": ([]interface {}) (len=48) {\n\t            \t+   (map[string]interface {}) (len=5) {\n\t            \t+    (string) (len=5) \"About\": (string) (len=25) \"FBqdwkwpYncTYQgwhMnyUqtei\",\n\t            \t+    (string) (len=5) \"Color\": (string) (len=25) \"SSindaNAHWEkBukErBsoXNSAX\",\n\t            \t+    (string) (len=2) \"ID\": (float64) 60,\n\t            \t+    (string) (len=4) \"Name\": (string) (len=25) \"kykZXjMpnPxCRdHHUlOIKlOEC\",\n\t            \t+    (string) (len=6) \"UserID\": (float64) 8\n\t            \t+   },\n\t            \t+   (map[string]interface {}) (len=5) {\n\t            \t+    (string) (len=5) \"About\": (string) (len=25) \"DQlDzkeQJScLPIwpwDrcRMknE\",\n\t            \t+    (string) (len=5) \"Color\": (string) (len=25) \"AhxrXMmRSdbIeAywJQMXeKxxT\",\n\t            \t+    (string) (len=2) \"ID\": (float64) 1,\n\t            \t+    (string) (len=4) \"Name\": (string) (len=25) \"iywbvukPXRwmdzNfLGEbjCcFE\",\n\t            \t+    (string) (len=6) \"UserID\": (float64) 94\n\t            \t+   },\n\t            \t+   (map[string]interface {}) (len=5) {\n\t            \t+    (string) (len=5) \"About\": (string) (len=25) \"DilxvBJzNwrQcrsVAuJdkFaNz\",\n\t            \t+    (string) (len=5) \"Color\": (string) (len=25) \"IyVKWsQDqUfyADWddPnuhRbyJ\",\n\t            \t+    (string) (len=2) \"ID\": (float64) 46,\n\t            \t+    (string) (len=4) \"Name\": (string) (len=25) \"gQoNzbRRLafHhDEwKtcqMlvif\",\n\t            \t+    (string) (len=6) \"UserID\": (float64) 57\n\t            \t+   },\n\t            \t+   (map[string]interface {}) (len=5) {\n\t            \t+    (string) (len=5) \"About\": (string) (len=25) \"BzXKpNiYEMfQsmpMBtwlDagmQ\",\n\t            \t+    (string) (len=5) \"Color\": (string) (len=25) \"gFgayYvtzMkGJDeEgOeOUtfmf\",\n\t            \t+    (string) (len=2) \"ID\": (float64) 40,\n\t            \t+    (string) (len=4) \"Name\": (string) (len=25) \"yTAkPWimHaNYCrHybsThPInyG\",\n\t            \t+    (string) (len=6) \"UserID\": (float64) 25\n\t            \t+   },\n\t            \t+   (map[string]interface {}) (len=5) {\n\t            \t+    (string) (len=5) \"About\": (string) (len=25) \"qpjLVSxtFDtNYkFWasVJWdkWS\",\n\t            \t+    (string) (len=5) \"Color\": (string) (len=25) \"OYXOqPuUcTpHBacrtyYrkVmJf\",\n\t            \t+    (string) (len=2) \"ID\": (float64) 97,\n\t            \t+    (string) (len=4) \"Name\": (string) (len=25) \"cXdtYjaPFRhYpXcFDIxwmWbwM\",\n\t            \t+    (string) (len=6) \"UserID\": (float64) 44\n\t            \t+   },\n\t            \t+   (map[string]interface {}) (len=5) {\n\t            \t+    (string) (len=5) \"About\": (string) (len=25) \"acqinUInZRwbgGSesFsXghAEc\",\n\t            \t+    (string) (len=5) \"Color\": (string) (len=25) \"zSYkDEHujMgtSWrbqsUzIgREX\",\n\t            \t+    (string) (len=2) \"ID\": (float64) 20,\n\t            \t+    (string) (len=4) \"Name\": (string) (len=25) \"FvNUdqLCPtzipNQQicbcrbRUU\",\n\t            \t+    (string) (len=6) \"UserID\": (float64) 99\n\t            \t+   },\n\t            \t+   (map[string]interface {}) (len=5) {\n\t            \t+    (string) (len=5) \"About\": (string) (len=25) \"kWAhVlghoDEfZLEXEaiOBfoha\",\n\t            \t+    (string) (len=5) \"Color\": (string) (len=25) \"CgZCNGWYZxHvWgyMASGehQgxK\",\n\t            \t+    (string) (len=2) \"ID\": (float64) 40,\n\t            \t+    (string) (len=4) \"Name\": (string) (len=25) \"oUkDRstEOAnfwrHZRskRzcjsG\",\n\t            \t+    (string) (len=6) \"UserID\": (float64) 24\n\t            \t+   },\n\t            \t+   (map[string]interface {}) (len=5) {\n\t            \t+    (string) (len=5) \"About\": (string) (len=25) \"MnRkAqCvJFtBieQBjraOulMFV\",\n\t            \t+    (string) (len=5) \"Color\": (string) (len=25) \"EkQojCOfPWbFDgYrbkSTnAFYg\",\n\t            \t+    (string) (len=2) \"ID\": (float64) 12,\n\t            \t+    (string) (len=4) \"Name\": (string) (len=25) \"vOqeiPsgidyMuygEwWpXkiRIO\",\n\t            \t+    (string) (len=6) \"UserID\": (float64) 79\n\t            \t+   },\n\t            \t+   (map[string]interface {}) (len=5) {\n\t            \t+    (string) (len=5) \"About\": (string) (len=25) \"eTmFfQqRjdtcERHQCFuHihspp\",\n\t            \t+    (string) (len=5) \"Color\": (string) (len=25) \"QLGMIwUSezmqTrgnkyetKoYgF\",\n\t            \t+    (string) (len=2) \"ID\": (float64) 7,\n\t            \t+    (string) (len=4) \"Name\": (string) (len=25) \"WGRmYFLLDTUKXZzsLDNWxTOhz\",\n\t            \t+    (string) (len=6) \"UserID\": (float64) 20\n\t            \t+   },\n\t            \t+   (map[string]interface {}) (len=5) {\n\t            \t+    (string) (len=5) \"About\": (string) (len=25) \"GNCUpxumMfaEVglXPoICthHxd\",\n\t            \t+    (string) (len=5) \"Color\": (string) (len=25) \"KwUhADqtyXGLRMYZGpfMgyMbp\",\n\t            \t+    (string) (len=2) \"ID\": (float64) 67,\n\t            \t+    (string) (len=4) \"Name\": (string) (len=25) \"DvkksZGiHwEzQTTSzikeCiJTE\",\n\t            \t+    (string) (len=6) \"UserID\": (float64) 43\n\t            \t+   },\n\t            \t+   (map[string]interface {}) (len=5) {\n\t            \t+    (string) (len=5) \"About\": (string) (len=25) \"DmFmkhqPOQWolwJSLVmPlwmyd\",\n\t            \t+    (string) (len=5) \"Color\": (string) (len=25) \"DpnBgkxFHmCmzujesUDtapiFf\",\n\t            \t+    (string) (len=2) \"ID\": (float64) 15,\n\t            \t+    (string) (len=4) \"Name\": (string) (len=25) \"xgsxspZZFiHqDBzTvuEmugpfT\",\n\t            \t+    (string) (len=6) \"UserID\": (float64) 95\n\t            \t+   },\n\t            \t+   (map[string]interface {}) (len=5) {\n\t            \t+    (string) (len=5) \"About\": (string) (len=25) \"WRPjsZQpFfmDTLfaEVAfvnZku\",\n\t            \t+    (string) (len=5) \"Color\": (string) (len=25) \"AMolqtClqCZlGYnbCgrZAEKYm\",\n\t            \t+    (string) (len=2) \"ID\": (float64) 47,\n\t            \t+    (string) (len=4) \"Name\": (string) (len=25) \"IORXqCjeJaIpNrxBgYuwNQEvs\",\n\t            \t+    (string) (len=6) \"UserID\": (float64) 61\n\t            \t+   },\n\t            \t+   (map[string]interface {}) (len=5) {\n\t            \t+    (string) (len=5) \"About\": (string) (len=25) \"cXIKhgwWusZWCYLGqOOyFFWZi\",\n\t            \t+    (string) (len=5) \"Color\": (string) (len=25) \"hOHFcCTUzCDkEuYhMTrzVMuOJ\",\n\t            \t+    (string) (len=2) \"ID\": (float64) 78,\n\t            \t+    (string) (len=4) \"Name\": (string) (len=25) \"BCwaAcTDohuDIxMyOmhDucDLJ\",\n\t            \t+    (string) (len=6) \"UserID\": (float64) 24\n\t            \t+   },\n\t            \t+   (map[string]interface {}) (len=5) {\n\t            \t+    (string) (len=5) \"About\": (string) (len=25) \"AJDvEGIVqHhWbfZLNlZCrakUV\",\n\t            \t+    (string) (len=5) \"Color\": (string) (len=25) \"gnxBrFmGFdfeCLtjoXbFnRnom\",\n\t            \t+    (string) (len=2) \"ID\": (float64) 32,\n\t            \t+    (string) (len=4) \"Name\": (string) (len=25) \"TUEsnkUvOvPmBzbrMVlHkJBgX\",\n\t            \t+    (string) (len=6) \"UserID\": (float64) 32\n\t            \t+   },\n\t            \t+   (map[string]interface {}) (len=5) {\n\t            \t+    (string) (len=5) \"About\": (string) (len=25) \"SlDaXdDQsaSzFJJEOqZRtIDWW\",\n\t            \t+    (string) (len=5) \"Color\": (string) (len=25) \"zotPbBCEWlZLzDphmCNwivMOD\",\n\t            \t+    (string) (len=2) \"ID\": (float64) 49,\n\t            \t+    (string) (len=4) \"Name\": (string) (len=25) \"zyKjsJpSbJZvEjQodffkbTQUn\",\n\t            \t+    (string) (len=6) \"UserID\": (float64) 65\n\t            \t+   },\n\t            \t+   (map[string]interface {}) (len=5) {\n\t            \t+    (string) (len=5) \"About\": (string) (len=25) \"AquvSfhZxaflPFCSNJcmgiOel\",\n\t            \t+    (string) (len=5) \"Color\": (string) (len=25) \"OhUAdxwYbaWoVaHKePmMVsQgn\",\n\t            \t+    (string) (len=2) \"ID\": (float64) 94,\n\t            \t+    (string) (len=4) \"Name\": (string) (len=25) \"YuZJAHgEQPYnblKXmFlLVJysV\",\n\t            \t+    (string) (len=6) \"UserID\": (float64) 40\n\t            \t+   },\n\t            \t+   (map[string]interface {}) (len=5) {\n\t            \t+    (string) (len=5) \"About\": (string) (len=25) \"zvxVoKyDtuiGpxneVMacnFgxB\",\n\t            \t+    (string) (len=5) \"Color\": (string) (len=25) \"NcygDnUtflioLfyXpntkpgZLO\",\n\t            \t+    (string) (len=2) \"ID\": (float64) 76,\n\t            \t+    (string) (len=4) \"Name\": (string) (len=25) \"OXgJnatcVWGOKgbfYnJqQwtaC\",\n\t            \t+    (string) (len=6) \"UserID\": (float64) 67\n\t            \t+   },\n\t            \t+   (map[string]interface {}) (len=5) {\n\t            \t+    (string) (len=5) \"About\": (string) (len=25) \"mYDEdCGKyBgGWNrgQcWiWmdOB\",\n\t            \t+    (string) (len=5) \"Color\": (string) (len=25) \"GexziBOwmXfzIywMgAqMzGuiU\",\n\t            \t+    (string) (len=2) \"ID\": (float64) 1,\n\t            \t+    (string) (len=4) \"Name\": (string) (len=25) \"EvZEOKGSNYcNuIIjykArugpuQ\",\n\t            \t+    (string) (len=6) \"UserID\": (float64) 7\n\t            \t+   },\n\t            \t+   (map[string]interface {}) (len=5) {\n\t            \t+    (string) (len=5) \"About\": (string) (len=25) \"tEbxklfeiLroOVdlzTJwsielG\",\n\t            \t+    (string) (len=5) \"Color\": (string) (len=25) \"ogdUsEwqJplBPxGFRSVdDiOHs\",\n\t            \t+    (string) (len=2) \"ID\": (float64) 77,\n\t            \t+    (string) (len=4) \"Name\": (string) (len=25) \"dKFdfLMQMzGLsorUDHBYatadh\",\n\t            \t+    (string) (len=6) \"UserID\": (float64) 26\n\t            \t+   },\n\t            \t+   (map[string]interface {}) (len=5) {\n\t            \t+    (string) (len=5) \"About\": (string) (len=25) \"lMMWdqjHgXtkHSyJhQdLDxOQA\",\n\t            \t+    (string) (len=5) \"Color\": (string) (len=25) \"VmadUrsyLJATgaaiJJeoRaljZ\",\n\t            \t+    (string) (len=2) \"ID\": (float64) 37,\n\t            \t+    (string) (len=4) \"Name\": (string) (len=25) \"IDDlbPXVMEaffnUkutJWpWSnM\",\n\t            \t+    (string) (len=6) \"UserID\": (float64) 1\n\t            \t+   },\n\t            \t+   (map[string]interface {}) (len=5) {\n\t            \t+    (string) (len=5) \"About\": (string) (len=25) \"DrMzDVcvHCtSGpyBGjndfZKMk\",\n\t            \t+    (string) (len=5) \"Color\": (string) (len=25) \"MJvLBgcnbtDgGlcIZZtcQTTtg\",\n\t            \t+    (string) (len=2) \"ID\": (float64) 16,\n\t            \t+    (string) (len=4) \"Name\": (string) (len=25) \"PmVXaBnYHUOOheTcRfYahjzOw\",\n\t            \t+    (string) (len=6) \"UserID\": (float64) 45\n\t            \t+   },\n\t            \t+   (map[string]interface {}) (len=5) {\n\t            \t+    (string) (len=5) \"About\": (string) (len=25) \"CTOCExlWuAHBZWxnIPrUpprPJ\",\n\t            \t+    (string) (len=5) \"Color\": (string) (len=25) \"tPKlAuMZbronlMkLAwVLSAfrG\",\n\t            \t+    (string) (len=2) \"ID\": (float64) 50,\n\t            \t+    (string) (len=4) \"Name\": (string) (len=25) \"VmSoqHzpmpZNxlnFtXFCgcHXa\",\n\t            \t+    (string) (len=6) \"UserID\": (float64) 45\n\t            \t+   },\n\t            \t+   (map[string]interface {}) (len=5) {\n\t            \t+    (string) (len=5) \"About\": (string) (len=25) \"wMsytEGWQCPNvBxGaNSGLgFuW\",\n\t            \t+    (string) (len=5) \"Color\": (string) (len=25) \"VSMOZXFDMdvPrfCFRQahZpeJi\",\n\t            \t+    (string) (len=2) \"ID\": (float64) 0,\n\t            \t+    (string) (len=4) \"Name\": (string) (len=25) \"byrCrWITDlCOUQFwbKASqqYOk\",\n\t            \t+    (string) (len=6) \"UserID\": (float64) 49\n\t            \t+   },\n\t            \t+   (map[string]interface {}) (len=5) {\n\t            \t+    (string) (len=5) \"About\": (string) (len=25) \"FVjtOcDFenwnPasNYArYiFJpU\",\n\t            \t+    (string) (len=5) \"Color\": (string) (len=25) \"lhIXdvKsAKTNHFPsCMmxaJcAw\",\n\t            \t+    (string) (len=2) \"ID\": (float64) 25,\n\t            \t+    (string) (len=4) \"Name\": (string) (len=25) \"puMZYvHrxpIgjALTadDknWeHb\",\n\t            \t+    (string) (len=6) \"UserID\": (float64) 41\n\t            \t+   },\n\t            \t+   (map[string]interface {}) (len=5) {\n\t            \t+    (string) (len=5) \"About\": (string) (len=25) \"MmZafZzDdbGQSNzCqhsDwFXcQ\",\n\t            \t+    (string) (len=5) \"Color\": (string) (len=25) \"zxoPtEzvPMdNMHmdDFvibSaUr\",\n\t            \t+    (string) (len=2) \"ID\": (float64) 90,\n\t            \t+    (string) (len=4) \"Name\": (string) (len=25) \"DYrbyUgUerxmPnucvyodadTkJ\",\n\t            \t+    (string) (len=6) \"UserID\": (float64) 21\n\t            \t+   },\n\t            \t+   (map[string]interface {}) (len=5) {\n\t            \t+    (string) (len=5) \"About\": (string) (len=25) \"hLzmfGogKYewiypMDSpCRGHkB\",\n\t            \t+    (string) (len=5) \"Color\": (string) (len=25) \"mcRSfXgNjLXPvrAfBRAmdANIT\",\n\t            \t+    (string) (len=2) \"ID\": (float64) 50,\n\t            \t+    (string) (len=4) \"Name\": (string) (len=25) \"FXvTbVTbKZxZYyMlULROLjXtP\",\n\t            \t+    (string) (len=6) \"UserID\": (float64) 24\n\t            \t+   },\n\t            \t+   (map[string]interface {}) (len=5) {\n\t            \t+    (string) (len=5) \"About\": (string) (len=25) \"EOBkDlbBmbGioyUGhSSxTKonk\",\n\t            \t+    (string) (len=5) \"Color\": (string) (len=25) \"dIborAbaRFLPzWQYpigfCLTtc\",\n\t            \t+    (string) (len=2) \"ID\": (float64) 49,\n\t            \t+    (string) (len=4) \"Name\": (string) (len=25) \"HoOMKKsZEOuTcHNbpRjfQkkJo\",\n\t            \t+    (string) (len=6) \"UserID\": (float64) 86\n\t            \t+   },\n\t            \t+   (map[string]interface {}) (len=5) {\n\t            \t+    (string) (len=5) \"About\": (string) (len=25) \"sJpEnQWROhvzZTGVJJrVdlxqz\",\n\t            \t+    (string) (len=5) \"Color\": (string) (len=25) \"xMSlwufhrbeAQDmKlzWpwOfqY\",\n\t            \t+    (string) (len=2) \"ID\": (float64) 2,\n\t            \t+    (string) (len=4) \"Name\": (string) (len=25) \"EhZgAqSVPkOWvtvDHkvwBoBxh\",\n\t            \t+    (string) (len=6) \"UserID\": (float64) 47\n\t            \t+   },\n\t            \t+   (map[string]interface {}) (len=5) {\n\t            \t+    (string) (len=5) \"About\": (string) (len=25) \"NmNhSwYoMCSFjxwSDuySwYJRT\",\n\t            \t+    (string) (len=5) \"Color\": (string) (len=25) \"HYIqFwIhYpMEsvyacmfXtVdSX\",\n\t            \t+    (string) (len=2) \"ID\": (float64) 83,\n\t            \t+    (string) (len=4) \"Name\": (string) (len=25) \"bKtaMKaTohdQxOIQLgmUETLGR\",\n\t            \t+    (string) (len=6) \"UserID\": (float64) 77\n\t            \t+   },\n\t            \t+   (map[string]interface {}) (len=5) {\n\t            \t+    (string) (len=5) \"About\": (string) (len=25) \"qDhMtHxFIaZdJdVyzIpYFucto\",\n\t            \t+    (string) (len=5) \"Color\": (string) (len=25) \"JIkjyoJMBAKKEcYqBFbzMeGDR\",\n\t            \t+    (string) (len=2) \"ID\": (float64) 43,\n\t            \t+    (string) (len=4) \"Name\": (string) (len=25) \"GcvmNdJsISAWPzkdZlgpCgPyk\",\n\t            \t+    (string) (len=6) \"UserID\": (float64) 1\n\t            \t+   },\n\t            \t+   (map[string]interface {}) (len=5) {\n\t            \t+    (string) (len=5) \"About\": (string) (len=25) \"pqggXcQFpGkKIjOHWdxcbRXsK\",\n\t            \t+    (string) (len=5) \"Color\": (string) (len=25) \"GWaEMvJiqbieQZZMydQPhTvAn\",\n\t            \t+    (string) (len=2) \"ID\": (float64) 92,\n\t            \t+    (string) (len=4) \"Name\": (string) (len=25) \"rWOKoHdNkAYnkcXFerycGXZaF\",\n\t            \t+    (string) (len=6) \"UserID\": (float64) 3\n\t            \t+   },\n\t            \t+   (map[string]interface {}) (len=5) {\n\t            \t+    (string) (len=5) \"About\": (string) (len=25) \"wbdPZNEMnOXKLgKQruVHyTNtp\",\n\t            \t+    (string) (len=5) \"Color\": (string) (len=25) \"jkApwbrepJccNGaOGHpuwlwxZ\",\n\t            \t+    (string) (len=2) \"ID\": (float64) 76,\n\t            \t+    (string) (len=4) \"Name\": (string) (len=25) \"rYxYUhOUuguQZqTGxLMovzUtH\",\n\t            \t+    (string) (len=6) \"UserID\": (float64) 24\n\t            \t+   },\n\t            \t+   (map[string]interface {}) (len=5) {\n\t            \t+    (string) (len=5) \"About\": (string) (len=25) \"jeXqLWSuNDPdCsvLHnoLCkBFV\",\n\t            \t+    (string) (len=5) \"Color\": (string) (len=25) \"UAOnqfkPdPKHlnScjkwYrjKYr\",\n\t            \t+    (string) (len=2) \"ID\": (float64) 19,\n\t            \t+    (string) (len=4) \"Name\": (string) (len=25) \"COdgBIzxaQlZglRoCqJiVxTAk\",\n\t            \t+    (string) (len=6) \"UserID\": (float64) 92\n\t            \t+   },\n\t            \t+   (map[string]interface {}) (len=5) {\n\t            \t+    (string) (len=5) \"About\": (string) (len=25) \"hANgjWfWkQjvsoURboarADLzk\",\n\t            \t+    (string) (len=5) \"Color\": (string) (len=25) \"tBwqKNsZZLkQWBnQEEkcIAaqw\",\n\t            \t+    (string) (len=2) \"ID\": (float64) 2,\n\t            \t+    (string) (len=4) \"Name\": (string) (len=25) \"TgjgyXcVLoIsDeGLppkrulGpV\",\n\t            \t+    (string) (len=6) \"UserID\": (float64) 43\n\t            \t+   },\n\t            \t+   (map[string]interface {}) (len=5) {\n\t            \t+    (string) (len=5) \"About\": (string) (len=25) \"LoExNLuhTtBmvhzrzVkNucnjl\",\n\t            \t+    (string) (len=5) \"Color\": (string) (len=25) \"ebuihoQwqZxFcltmvLESjovGx\",\n\t            \t+    (string) (len=2) \"ID\": (float64) 96,\n\t            \t+    (string) (len=4) \"Name\": (string) (len=25) \"sUNUHYwhTYFhoSBKlpTvItxjS\",\n\t            \t+    (string) (len=6) \"UserID\": (float64) 48\n\t            \t+   },\n\t            \t+   (map[string]interface {}) (len=5) {\n\t            \t+    (string) (len=5) \"About\": (string) (len=25) \"XZJqlcwNAJUShGxmmTgDYZaHy\",\n\t            \t+    (string) (len=5) \"Color\": (string) (len=25) \"nxWXWgsnTFMIWqdleGjsKOGHD\",\n\t            \t+    (string) (len=2) \"ID\": (float64) 55,\n\t            \t+    (string) (len=4) \"Name\": (string) (len=25) \"WouGVQxDMxnYKSLVApdbhaqTp\",\n\t            \t+    (string) (len=6) \"UserID\": (float64) 57\n\t            \t+   },\n\t            \t+   (map[string]interface {}) (len=5) {\n\t            \t+    (string) (len=5) \"About\": (string) (len=25) \"rZVdfehCwPhekZRRVZCnTRtIn\",\n\t            \t+    (string) (len=5) \"Color\": (string) (len=25) \"ysjddhhTdvDcRgGshOhuyWTDc\",\n\t            \t+    (string) (len=2) \"ID\": (float64) 16,\n\t            \t+    (string) (len=4) \"Name\": (string) (len=25) \"miUIIuhwiXCsttHuJWWoXDuCz\",\n\t            \t+    (string) (len=6) \"UserID\": (float64) 76\n\t            \t+   },\n\t            \t+   (map[string]interface {}) (len=5) {\n\t            \t+    (string) (len=5) \"About\": (string) (len=25) \"uGHkiFXWCqiBKNsyStqZJhsSh\",\n\t            \t+    (string) (len=5) \"Color\": (string) (len=25) \"YCpCayxilRbnTdujYuKrMOGYl\",\n\t            \t+    (string) (len=2) \"ID\": (float64) 76,\n\t            \t+    (string) (len=4) \"Name\": (string) (len=25) \"pELHXvATHBSOUCyvfmyNaSBbW\",\n\t            \t+    (string) (len=6) \"UserID\": (float64) 93\n\t            \t+   },\n\t            \t+   (map[string]interface {}) (len=5) {\n\t            \t+    (string) (len=5) \"About\": (string) (len=25) \"wwYjjCyvwDSMnAQxmQBdTeYRd\",\n\t            \t+    (string) (len=5) \"Color\": (string) (len=25) \"eCWtnvWmkUxGzHsfrRHRDoJyx\",\n\t            \t+    (string) (len=2) \"ID\": (float64) 94,\n\t            \t+    (string) (len=4) \"Name\": (string) (len=25) \"ZUforRAvxSBwdZisqmGyQHGoG\",\n\t            \t+    (string) (len=6) \"UserID\": (float64) 30\n\t            \t+   },\n\t            \t+   (map[string]interface {}) (len=5) {\n\t            \t+    (string) (len=5) \"About\": (string) (len=25) \"xyfDfcYBYssSORvmikhSLcuyG\",\n\t            \t+    (string) (len=5) \"Color\": (string) (len=25) \"eoGoZAtKQnczfPPWPughOSEgI\",\n\t            \t+    (string) (len=2) \"ID\": (float64) 53,\n\t            \t+    (string) (len=4) \"Name\": (string) (len=25) \"dmsWUCgBIjUSvnekgeoqrXKYR\",\n\t            \t+    (string) (len=6) \"UserID\": (float64) 80\n\t            \t+   },\n\t            \t+   (map[string]interface {}) (len=5) {\n\t            \t+    (string) (len=5) \"About\": (string) (len=25) \"pQiOOONtbVaSQwMoyybWuoVBz\",\n\t            \t+    (string) (len=5) \"Color\": (string) (len=25) \"rgGhWzoaJRmxhLisvqgTuDJXz\",\n\t            \t+    (string) (len=2) \"ID\": (float64) 4,\n\t            \t+    (string) (len=4) \"Name\": (string) (len=25) \"NSuXYKfilgvHBDWzCBiFQVwWf\",\n\t            \t+    (string) (len=6) \"UserID\": (float64) 49\n\t            \t+   },\n\t            \t+   (map[string]interface {}) (len=5) {\n\t            \t+    (string) (len=5) \"About\": (string) (len=25) \"gfgbOxyMNTFzuZLMcneczCMTu\",\n\t            \t+    (string) (len=5) \"Color\": (string) (len=25) \"GdvXJhxUsHarvZdDyGjjcjErO\",\n\t            \t+    (string) (len=2) \"ID\": (float64) 10,\n\t            \t+    (string) (len=4) \"Name\": (string) (len=25) \"MpPcxFPsApIbTGpMLzoUzHFvW\",\n\t            \t+    (string) (len=6) \"UserID\": (float64) 74\n\t            \t+   },\n\t            \t+   (map[string]interface {}) (len=5) {\n\t            \t+    (string) (len=5) \"About\": (string) (len=25) \"ekoFctoxzNVzioSuGZZdbZUnw\",\n\t            \t+    (string) (len=5) \"Color\": (string) (len=25) \"sUtfNMwwIofrigIiCSoxCfmbH\",\n\t            \t+    (string) (len=2) \"ID\": (float64) 76,\n\t            \t+    (string) (len=4) \"Name\": (string) (len=25) \"hyliSrckXcoKArloyQdEWRsSs\",\n\t            \t+    (string) (len=6) \"UserID\": (float64) 15\n\t            \t+   },\n\t            \t+   (map[string]interface {}) (len=5) {\n\t            \t+    (string) (len=5) \"About\": (string) (len=25) \"lJZMuuGEdElVCrXvchuwqGbPj\",\n\t            \t+    (string) (len=5) \"Color\": (string) (len=25) \"JUxogvLyZphBaQzTrEcAMyBYO\",\n\t            \t+    (string) (len=2) \"ID\": (float64) 15,\n\t            \t+    (string) (len=4) \"Name\": (string) (len=25) \"dXmulEWSOYVSeFrFQjBpKpIhz\",\n\t            \t+    (string) (len=6) \"UserID\": (float64) 88\n\t            \t+   },\n\t            \t+   (map[string]interface {}) (len=5) {\n\t            \t+    (string) (len=5) \"About\": (string) (len=25) \"rkcSpIysBucfWbEQMLMhXiAmA\",\n\t            \t+    (string) (len=5) \"Color\": (string) (len=25) \"uKAudzmrtlOwzNaMicBfGULoR\",\n\t            \t+    (string) (len=2) \"ID\": (float64) 10,\n\t            \t+    (string) (len=4) \"Name\": (string) (len=25) \"wVWjzEbVxqPKMtYuPTLvZgNFy\",\n\t            \t+    (string) (len=6) \"UserID\": (float64) 34\n\t            \t+   },\n\t            \t+   (map[string]interface {}) (len=5) {\n\t            \t+    (string) (len=5) \"About\": (string) (len=25) \"JcsKTqdUgGkdSqUjVdFioMYCO\",\n\t            \t+    (string) (len=5) \"Color\": (string) (len=25) \"SINnkFDYIDFWolYjzSpfflrHe\",\n\t            \t+    (string) (len=2) \"ID\": (float64) 33,\n\t            \t+    (string) (len=4) \"Name\": (string) (len=25) \"zzAgmHRnBOgaqCFvZSAqrdedD\",\n\t            \t+    (string) (len=6) \"UserID\": (float64) 81\n\t            \t+   },\n\t            \t+   (map[string]interface {}) (len=5) {\n\t            \t+    (string) (len=5) \"About\": (string) (len=25) \"VOnBZXtRtAVADUktahQrGXrBM\",\n\t            \t+    (string) (len=5) \"Color\": (string) (len=25) \"HuoEzfLlpJDtRPhTGLpMBKCzC\",\n\t            \t+    (string) (len=2) \"ID\": (float64) 2,\n\t            \t+    (string) (len=4) \"Name\": (string) (len=25) \"BaXSywAdJczPtnNJZxilsBwxw\",\n\t            \t+    (string) (len=6) \"UserID\": (float64) 11\n\t            \t+   },\n\t            \t+   (map[string]interface {}) (len=5) {\n\t            \t+    (string) (len=5) \"About\": (string) (len=25) \"dMOFhZBKiTJHsFkvjDsmxCGYK\",\n\t            \t+    (string) (len=5) \"Color\": (string) (len=25) \"WOEiZGVbIWZWunzJBKGBQdwfV\",\n\t            \t+    (string) (len=2) \"ID\": (float64) 44,\n\t            \t+    (string) (len=4) \"Name\": (string) (len=25) \"aBxOyAkeLPfzYNJDuhkTjUdPz\",\n\t            \t+    (string) (len=6) \"UserID\": (float64) 75\n\t            \t+   }\n\t            \t   },\n\tTest:       \tTestGetEntry\n"},"start":1696422680459,"stop":1696422680463,"uuid":"ec14aa6e-62b1-11ee-9140-3e22fbd4bb58","historyId":"9c8c3129ade149bdd5ec782e560977bd","testCaseId":"9ca3a3a7e0fc7d6b27aca67332dc7cfb","labels":[{"name":"language","value":"go1.21.0"},{"name":"framework","value":"Allure-Go@v0.6.0"},{"name":"host","value":"d-neumoin"},{"name":"thread","value":"TestEntryTestIntegrationSuite/EntryTestIntegrationSuite/TestGetEntry"},{"name":"suite","value":"EntryTestIntegrationSuite"},{"name":"package","value":"timetracker/integration_test/delivery_usecase"}],"steps":[{"name":"REQUIRE: error while prepare expDataJson","status":"passed","start":1696422680460,"stop":1696422680460,"parameters":[{"name":"Actual","value":"\u003cnil\u003e"}]},{"name":"ASSERT: No Error","status":"passed","start":1696422680460,"stop":1696422680460,"parameters":[{"name":"Actual","value":"\u003cnil\u003e"}]},{"name":"REQUIRE: No Error","status":"passed","start":1696422680460,"stop":1696422680460,"parameters":[{"name":"Actual","value":"\u003cnil\u003e"}]},{"name":"ASSERT: Equal","status":"passed","start":1696422680460,"stop":1696422680460,"parameters":[{"name":"Expected","value":"200"},{"name":"Actual","value":"200"}]},{"name":"ASSERT: JSON Equal","status":"failed","start":1696422680460,"stop":1696422680460,"parameters":[{"name":"Expected","value":"{\"body\":{\"description\":\"entry\",\"duration\":\"2h0m0s\",\"id\":1,\"project_id\":null,\"tag_list\":[],\"time_end\":\"2021-08-15T16:30:45+03:00\",\"time_start\":\"2021-08-15T14:30:45+03:00\",\"user_id\":1}}"},{"name":"Actual","value":"{\"body\":{\"id\":1,\"user_id\":1,\"project_id\":null,\"description\":\"entry\",\"tag_list\":[{\"ID\":60,\"UserID\":8,\"Name\":\"kykZXjMpnPxCRdHHUlOIKlOEC\",\"About\":\"FBqdwkwpYncTYQgwhMnyUqtei\",\"Color\":\"SSindaNAHWEkBukErBsoXNSAX\"},{\"ID\":1,\"UserID\":94,\"Name\":\"iywbvukPXRwmdzNfLGEbjCcFE\",\"About\":\"DQlDzkeQJScLPIwpwDrcRMknE\",\"Color\":\"AhxrXMmRSdbIeAywJQMXeKxxT\"},{\"ID\":46,\"UserID\":57,\"Name\":\"gQoNzbRRLafHhDEwKtcqMlvif\",\"About\":\"DilxvBJzNwrQcrsVAuJdkFaNz\",\"Color\":\"IyVKWsQDqUfyADWddPnuhRbyJ\"},{\"ID\":40,\"UserID\":25,\"Name\":\"yTAkPWimHaNYCrHybsThPInyG\",\"About\":\"BzXKpNiYEMfQsmpMBtwlDagmQ\",\"Color\":\"gFgayYvtzMkGJDeEgOeOUtfmf\"},{\"ID\":97,\"UserID\":44,\"Name\":\"cXdtYjaPFRhYpXcFDIxwmWbwM\",\"About\":\"qpjLVSxtFDtNYkFWasVJWdkWS\",\"Color\":\"OYXOqPuUcTpHBacrtyYrkVmJf\"},{\"ID\":20,\"UserID\":99,\"Name\":\"FvNUdqLCPtzipNQQicbcrbRUU\",\"About\":\"acqinUInZRwbgGSesFsXghAEc\",\"Color\":\"zSYkDEHujMgtSWrbqsUzIgREX\"},{\"ID\":40,\"UserID\":24,\"Name\":\"oUkDRstEOAnfwrHZRskRzcjsG\",\"About\":\"kWAhVlghoDEfZLEXEaiOBfoha\",\"Color\":\"CgZCNGWYZxHvWgyMASGehQgxK\"},{\"ID\":12,\"UserID\":79,\"Name\":\"vOqeiPsgidyMuygEwWpXkiRIO\",\"About\":\"MnRkAqCvJFtBieQBjraOulMFV\",\"Color\":\"EkQojCOfPWbFDgYrbkSTnAFYg\"},{\"ID\":7,\"UserID\":20,\"Name\":\"WGRmYFLLDTUKXZzsLDNWxTOhz\",\"About\":\"eTmFfQqRjdtcERHQCFuHihspp\",\"Color\":\"QLGMIwUSezmqTrgnkyetKoYgF\"},{\"ID\":67,\"UserID\":43,\"Name\":\"DvkksZGiHwEzQTTSzikeCiJTE\",\"About\":\"GNCUpxumMfaEVglXPoICthHxd\",\"Color\":\"KwUhADqtyXGLRMYZGpfMgyMbp\"},{\"ID\":15,\"UserID\":95,\"Name\":\"xgsxspZZFiHqDBzTvuEmugpfT\",\"About\":\"DmFmkhqPOQWolwJSLVmPlwmyd\",\"Color\":\"DpnBgkxFHmCmzujesUDtapiFf\"},{\"ID\":47,\"UserID\":61,\"Name\":\"IORXqCjeJaIpNrxBgYuwNQEvs\",\"About\":\"WRPjsZQpFfmDTLfaEVAfvnZku\",\"Color\":\"AMolqtClqCZlGYnbCgrZAEKYm\"},{\"ID\":78,\"UserID\":24,\"Name\":\"BCwaAcTDohuDIxMyOmhDucDLJ\",\"About\":\"cXIKhgwWusZWCYLGqOOyFFWZi\",\"Color\":\"hOHFcCTUzCDkEuYhMTrzVMuOJ\"},{\"ID\":32,\"UserID\":32,\"Name\":\"TUEsnkUvOvPmBzbrMVlHkJBgX\",\"About\":\"AJDvEGIVqHhWbfZLNlZCrakUV\",\"Color\":\"gnxBrFmGFdfeCLtjoXbFnRnom\"},{\"ID\":49,\"UserID\":65,\"Name\":\"zyKjsJpSbJZvEjQodffkbTQUn\",\"About\":\"SlDaXdDQsaSzFJJEOqZRtIDWW\",\"Color\":\"zotPbBCEWlZLzDphmCNwivMOD\"},{\"ID\":94,\"UserID\":40,\"Name\":\"YuZJAHgEQPYnblKXmFlLVJysV\",\"About\":\"AquvSfhZxaflPFCSNJcmgiOel\",\"Color\":\"OhUAdxwYbaWoVaHKePmMVsQgn\"},{\"ID\":76,\"UserID\":67,\"Name\":\"OXgJnatcVWGOKgbfYnJqQwtaC\",\"About\":\"zvxVoKyDtuiGpxneVMacnFgxB\",\"Color\":\"NcygDnUtflioLfyXpntkpgZLO\"},{\"ID\":1,\"UserID\":7,\"Name\":\"EvZEOKGSNYcNuIIjykArugpuQ\",\"About\":\"mYDEdCGKyBgGWNrgQcWiWmdOB\",\"Color\":\"GexziBOwmXfzIywMgAqMzGuiU\"},{\"ID\":77,\"UserID\":26,\"Name\":\"dKFdfLMQMzGLsorUDHBYatadh\",\"About\":\"tEbxklfeiLroOVdlzTJwsielG\",\"Color\":\"ogdUsEwqJplBPxGFRSVdDiOHs\"},{\"ID\":37,\"UserID\":1,\"Name\":\"IDDlbPXVMEaffnUkutJWpWSnM\",\"About\":\"lMMWdqjHgXtkHSyJhQdLDxOQA\",\"Color\":\"VmadUrsyLJATgaaiJJeoRaljZ\"},{\"ID\":16,\"UserID\":45,\"Name\":\"PmVXaBnYHUOOheTcRfYahjzOw\",\"About\":\"DrMzDVcvHCtSGpyBGjndfZKMk\",\"Color\":\"MJvLBgcnbtDgGlcIZZtcQTTtg\"},{\"ID\":50,\"UserID\":45,\"Name\":\"VmSoqHzpmpZNxlnFtXFCgcHXa\",\"About\":\"CTOCExlWuAHBZWxnIPrUpprPJ\",\"Color\":\"tPKlAuMZbronlMkLAwVLSAfrG\"},{\"ID\":0,\"UserID\":49,\"Name\":\"byrCrWITDlCOUQFwbKASqqYOk\",\"About\":\"wMsytEGWQCPNvBxGaNSGLgFuW\",\"Color\":\"VSMOZXFDMdvPrfCFRQahZpeJi\"},{\"ID\":25,\"UserID\":41,\"Name\":\"puMZYvHrxpIgjALTadDknWeHb\",\"About\":\"FVjtOcDFenwnPasNYArYiFJpU\",\"Color\":\"lhIXdvKsAKTNHFPsCMmxaJcAw\"},{\"ID\":90,\"UserID\":21,\"Name\":\"DYrbyUgUerxmPnucvyodadTkJ\",\"About\":\"MmZafZzDdbGQSNzCqhsDwFXcQ\",\"Color\":\"zxoPtEzvPMdNMHmdDFvibSaUr\"},{\"ID\":50,\"UserID\":24,\"Name\":\"FXvTbVTbKZxZYyMlULROLjXtP\",\"About\":\"hLzmfGogKYewiypMDSpCRGHkB\",\"Color\":\"mcRSfXgNjLXPvrAfBRAmdANIT\"},{\"ID\":49,\"UserID\":86,\"Name\":\"HoOMKKsZEOuTcHNbpRjfQkkJo\",\"About\":\"EOBkDlbBmbGioyUGhSSxTKonk\",\"Color\":\"dIborAbaRFLPzWQYpigfCLTtc\"},{\"ID\":2,\"UserID\":47,\"Name\":\"EhZgAqSVPkOWvtvDHkvwBoBxh\",\"About\":\"sJpEnQWROhvzZTGVJJrVdlxqz\",\"Color\":\"xMSlwufhrbeAQDmKlzWpwOfqY\"},{\"ID\":83,\"UserID\":77,\"Name\":\"bKtaMKaTohdQxOIQLgmUETLGR\",\"About\":\"NmNhSwYoMCSFjxwSDuySwYJRT\",\"Color\":\"HYIqFwIhYpMEsvyacmfXtVdSX\"},{\"ID\":43,\"UserID\":1,\"Name\":\"GcvmNdJsISAWPzkdZlgpCgPyk\",\"About\":\"qDhMtHxFIaZdJdVyzIpYFucto\",\"Color\":\"JIkjyoJMBAKKEcYqBFbzMeGDR\"},{\"ID\":92,\"UserID\":3,\"Name\":\"rWOKoHdNkAYnkcXFerycGXZaF\",\"About\":\"pqggXcQFpGkKIjOHWdxcbRXsK\",\"Color\":\"GWaEMvJiqbieQZZMydQPhTvAn\"},{\"ID\":76,\"UserID\":24,\"Name\":\"rYxYUhOUuguQZqTGxLMovzUtH\",\"About\":\"wbdPZNEMnOXKLgKQruVHyTNtp\",\"Color\":\"jkApwbrepJccNGaOGHpuwlwxZ\"},{\"ID\":19,\"UserID\":92,\"Name\":\"COdgBIzxaQlZglRoCqJiVxTAk\",\"About\":\"jeXqLWSuNDPdCsvLHnoLCkBFV\",\"Color\":\"UAOnqfkPdPKHlnScjkwYrjKYr\"},{\"ID\":2,\"UserID\":43,\"Name\":\"TgjgyXcVLoIsDeGLppkrulGpV\",\"About\":\"hANgjWfWkQjvsoURboarADLzk\",\"Color\":\"tBwqKNsZZLkQWBnQEEkcIAaqw\"},{\"ID\":96,\"UserID\":48,\"Name\":\"sUNUHYwhTYFhoSBKlpTvItxjS\",\"About\":\"LoExNLuhTtBmvhzrzVkNucnjl\",\"Color\":\"ebuihoQwqZxFcltmvLESjovGx\"},{\"ID\":55,\"UserID\":57,\"Name\":\"WouGVQxDMxnYKSLVApdbhaqTp\",\"About\":\"XZJqlcwNAJUShGxmmTgDYZaHy\",\"Color\":\"nxWXWgsnTFMIWqdleGjsKOGHD\"},{\"ID\":16,\"UserID\":76,\"Name\":\"miUIIuhwiXCsttHuJWWoXDuCz\",\"About\":\"rZVdfehCwPhekZRRVZCnTRtIn\",\"Color\":\"ysjddhhTdvDcRgGshOhuyWTDc\"},{\"ID\":76,\"UserID\":93,\"Name\":\"pELHXvATHBSOUCyvfmyNaSBbW\",\"About\":\"uGHkiFXWCqiBKNsyStqZJhsSh\",\"Color\":\"YCpCayxilRbnTdujYuKrMOGYl\"},{\"ID\":94,\"UserID\":30,\"Name\":\"ZUforRAvxSBwdZisqmGyQHGoG\",\"About\":\"wwYjjCyvwDSMnAQxmQBdTeYRd\",\"Color\":\"eCWtnvWmkUxGzHsfrRHRDoJyx\"},{\"ID\":53,\"UserID\":80,\"Name\":\"dmsWUCgBIjUSvnekgeoqrXKYR\",\"About\":\"xyfDfcYBYssSORvmikhSLcuyG\",\"Color\":\"eoGoZAtKQnczfPPWPughOSEgI\"},{\"ID\":4,\"UserID\":49,\"Name\":\"NSuXYKfilgvHBDWzCBiFQVwWf\",\"About\":\"pQiOOONtbVaSQwMoyybWuoVBz\",\"Color\":\"rgGhWzoaJRmxhLisvqgTuDJXz\"},{\"ID\":10,\"UserID\":74,\"Name\":\"MpPcxFPsApIbTGpMLzoUzHFvW\",\"About\":\"gfgbOxyMNTFzuZLMcneczCMTu\",\"Color\":\"GdvXJhxUsHarvZdDyGjjcjErO\"},{\"ID\":76,\"UserID\":15,\"Name\":\"hyliSrckXcoKArloyQdEWRsSs\",\"About\":\"ekoFctoxzNVzioSuGZZdbZUnw\",\"Color\":\"sUtfNMwwIofrigIiCSoxCfmbH\"},{\"ID\":15,\"UserID\":88,\"Name\":\"dXmulEWSOYVSeFrFQjBpKpIhz\",\"About\":\"lJZMuuGEdElVCrXvchuwqGbPj\",\"Color\":\"JUxogvLyZphBaQzTrEcAMyBYO\"},{\"ID\":10,\"UserID\":34,\"Name\":\"wVWjzEbVxqPKMtYuPTLvZgNFy\",\"About\":\"rkcSpIysBucfWbEQMLMhXiAmA\",\"Color\":\"uKAudzmrtlOwzNaMicBfGULoR\"},{\"ID\":33,\"UserID\":81,\"Name\":\"zzAgmHRnBOgaqCFvZSAqrdedD\",\"About\":\"JcsKTqdUgGkdSqUjVdFioMYCO\",\"Color\":\"SINnkFDYIDFWolYjzSpfflrHe\"},{\"ID\":2,\"UserID\":11,\"Name\":\"BaXSywAdJczPtnNJZxilsBwxw\",\"About\":\"VOnBZXtRtAVADUktahQrGXrBM\",\"Color\":\"HuoEzfLlpJDtRPhTGLpMBKCzC\"},{\"ID\":44,\"UserID\":75,\"Name\":\"aBxOyAkeLPfzYNJDuhkTjUdPz\",\"About\":\"dMOFhZBKiTJHsFkvjDsmxCGYK\",\"Color\":\"WOEiZGVbIWZWunzJBKGBQdwfV\"}],\"time_start\":\"2021-08-15T14:30:45+03:00\",\"time_end\":\"2021-08-15T16:30:45+03:00\",\"duration\":\"2h0m0s\"}}\n"}]}]}